{"facets": [{"filters": [{"count": 8, "not": null, "off": null, "on": "https://www.loc.gov/search/?c=200&fo=json&sb=shelf-id&sq=group:gmd.mar+AND+number_source_modified:%5B2021-10-07+TO+2021-10-08%5D", "title": "true"}], "title": "Available Online", "type": "digitized"}, {"filters": [{"count": 8, "not": "https://www.loc.gov/search/?all=true&c=200&fa=original-format!:map&fo=json&sb=shelf-id&sq=group:gmd.mar+AND+number_source_modified:%5B2021-10-07+TO+2021-10-08%5D", "off": null, "on": "https://www.loc.gov/maps/?all=true&c=200&fo=json&sb=shelf-id&sq=group:gmd.mar+AND+number_source_modified:%5B2021-10-07+TO+2021-10-08%5D", "title": "map"}], "title": "Original Format", "type": "original-format"}, {"filters": [{"count": 8, "not": "https://www.loc.gov/search/?all=true&c=200&fa=online-format!:image&fo=json&sb=shelf-id&sq=group:gmd.mar+AND+number_source_modified:%5B2021-10-07+TO+2021-10-08%5D", "off": null, "on": "https://www.loc.gov/search/?all=true&c=200&fa=online-format:image&fo=json&sb=shelf-id&sq=group:gmd.mar+AND+number_source_modified:%5B2021-10-07+TO+2021-10-08%5D", "title": "image"}], "title": "Online Format", "type": "online-format"}, {"filters": [{"count": 1, "not": null, "off": null, "on": "https://www.loc.gov/search/?all=true&c=200&dates=2000/2099&fo=json&sb=shelf-id&sq=group:gmd.mar+AND+number_source_modified:%5B2021-10-07+TO+2021-10-08%5D", "term": "2000-01-01T00:00:00Z", "title": "2000 to 2099"}, {"count": 7, "not": null, "off": null, "on": "https://www.loc.gov/search/?all=true&c=200&dates=1800/1899&fo=json&sb=shelf-id&sq=group:gmd.mar+AND+number_source_modified:%5B2021-10-07+TO+2021-10-08%5D", "term": "1800-01-01T00:00:00Z", "title": "1800 to 1899"}], "title": "Date", "type": "dates"}, {"filters": [{"count": 7, "not": "https://www.loc.gov/search/?all=true&c=200&fa=location!:united+states&fo=json&sb=shelf-id&sq=group:gmd.mar+AND+number_source_modified:%5B2021-10-07+TO+2021-10-08%5D", "off": null, "on": "https://www.loc.gov/search/?all=true&c=200&fa=location:united+states&fo=json&sb=shelf-id&sq=group:gmd.mar+AND+number_source_modified:%5B2021-10-07+TO+2021-10-08%5D", "title": "united states"}, {"count": 5, "not": "https://www.loc.gov/search/?all=true&c=200&fa=location!:new+york&fo=json&sb=shelf-id&sq=group:gmd.mar+AND+number_source_modified:%5B2021-10-07+TO+2021-10-08%5D", "off": null, "on": "https://www.loc.gov/search/?all=true&c=200&fa=location:new+york&fo=json&sb=shelf-id&sq=group:gmd.mar+AND+number_source_modified:%5B2021-10-07+TO+2021-10-08%5D", "title": "new york"}, {"count": 5, "not": "https://www.loc.gov/search/?all=true&c=200&fa=location!:new+york+%28state%29&fo=json&sb=shelf-id&sq=group:gmd.mar+AND+number_source_modified:%5B2021-10-07+TO+2021-10-08%5D", "off": null, "on": "https://www.loc.gov/search/?all=true&c=200&fa=location:new+york+%28state%29&fo=json&sb=shelf-id&sq=group:gmd.mar+AND+number_source_modified:%5B2021-10-07+TO+2021-10-08%5D", "title": "new york (state)"}, {"count": 5, "not": "https://www.loc.gov/search/?all=true&c=200&fa=location!:staten+island&fo=json&sb=shelf-id&sq=group:gmd.mar+AND+number_source_modified:%5B2021-10-07+TO+2021-10-08%5D", "off": null, "on": "https://www.loc.gov/search/?all=true&c=200&fa=location:staten+island&fo=json&sb=shelf-id&sq=group:gmd.mar+AND+number_source_modified:%5B2021-10-07+TO+2021-10-08%5D", "title": "staten island"}, {"count": 1, "not": "https://www.loc.gov/search/?all=true&c=200&fa=location!:amecameca+region&fo=json&sb=shelf-id&sq=group:gmd.mar+AND+number_source_modified:%5B2021-10-07+TO+2021-10-08%5D", "off": null, "on": "https://www.loc.gov/search/?all=true&c=200&fa=location:amecameca+region&fo=json&sb=shelf-id&sq=group:gmd.mar+AND+number_source_modified:%5B2021-10-07+TO+2021-10-08%5D", "title": "amecameca region"}, {"count": 1, "not": "https://www.loc.gov/search/?all=true&c=200&fa=location!:hopewell+culture+national+historical+park&fo=json&sb=shelf-id&sq=group:gmd.mar+AND+number_source_modified:%5B2021-10-07+TO+2021-10-08%5D", "off": null, "on": "https://www.loc.gov/search/?all=true&c=200&fa=location:hopewell+culture+national+historical+park&fo=json&sb=shelf-id&sq=group:gmd.mar+AND+number_source_modified:%5B2021-10-07+TO+2021-10-08%5D", "title": "hopewell culture national historical park"}, {"count": 1, "not": "https://www.loc.gov/search/?all=true&c=200&fa=location!:mexico&fo=json&sb=shelf-id&sq=group:gmd.mar+AND+number_source_modified:%5B2021-10-07+TO+2021-10-08%5D", "off": null, "on": "https://www.loc.gov/search/?all=true&c=200&fa=location:mexico&fo=json&sb=shelf-id&sq=group:gmd.mar+AND+number_source_modified:%5B2021-10-07+TO+2021-10-08%5D", "title": "mexico"}, {"count": 1, "not": "https://www.loc.gov/search/?all=true&c=200&fa=location!:ohio&fo=json&sb=shelf-id&sq=group:gmd.mar+AND+number_source_modified:%5B2021-10-07+TO+2021-10-08%5D", "off": null, "on": "https://www.loc.gov/search/?all=true&c=200&fa=location:ohio&fo=json&sb=shelf-id&sq=group:gmd.mar+AND+number_source_modified:%5B2021-10-07+TO+2021-10-08%5D", "title": "ohio"}, {"count": 1, "not": "https://www.loc.gov/search/?all=true&c=200&fa=location!:pennsylvania&fo=json&sb=shelf-id&sq=group:gmd.mar+AND+number_source_modified:%5B2021-10-07+TO+2021-10-08%5D", "off": null, "on": "https://www.loc.gov/search/?all=true&c=200&fa=location:pennsylvania&fo=json&sb=shelf-id&sq=group:gmd.mar+AND+number_source_modified:%5B2021-10-07+TO+2021-10-08%5D", "title": "pennsylvania"}, {"count": 1, "not": "https://www.loc.gov/search/?all=true&c=200&fa=location!:philadelphia&fo=json&sb=shelf-id&sq=group:gmd.mar+AND+number_source_modified:%5B2021-10-07+TO+2021-10-08%5D", "off": null, "on": "https://www.loc.gov/search/?all=true&c=200&fa=location:philadelphia&fo=json&sb=shelf-id&sq=group:gmd.mar+AND+number_source_modified:%5B2021-10-07+TO+2021-10-08%5D", "title": "philadelphia"}], "index": "https://www.loc.gov/search/index/location/?all=true&c=200&fo=json&sq=group:gmd.mar+AND+number_source_modified:%5B2021-10-07+TO+2021-10-08%5D", "title": "Location", "type": "location"}, {"filters": [{"count": 8, "not": "https://www.loc.gov/search/?all=true&c=200&fa=partof!:american+memory&fo=json&sb=shelf-id&sq=group:gmd.mar+AND+number_source_modified:%5B2021-10-07+TO+2021-10-08%5D", "off": null, "on": "https://www.loc.gov/search/?all=true&c=200&fa=partof:american+memory&fo=json&sb=shelf-id&sq=group:gmd.mar+AND+number_source_modified:%5B2021-10-07+TO+2021-10-08%5D", "title": "american memory"}, {"count": 8, "not": "https://www.loc.gov/search/?all=true&c=200&fa=partof!:catalog&fo=json&sb=shelf-id&sq=group:gmd.mar+AND+number_source_modified:%5B2021-10-07+TO+2021-10-08%5D", "off": null, "on": "https://www.loc.gov/search/?all=true&c=200&fa=partof:catalog&fo=json&sb=shelf-id&sq=group:gmd.mar+AND+number_source_modified:%5B2021-10-07+TO+2021-10-08%5D", "title": "catalog"}, {"count": 8, "not": "https://www.loc.gov/search/?all=true&c=200&fa=partof!:geography+and+map+division&fo=json&sb=shelf-id&sq=group:gmd.mar+AND+number_source_modified:%5B2021-10-07+TO+2021-10-08%5D", "off": null, "on": "https://www.loc.gov/search/?all=true&c=200&fa=partof:geography+and+map+division&fo=json&sb=shelf-id&sq=group:gmd.mar+AND+number_source_modified:%5B2021-10-07+TO+2021-10-08%5D", "title": "geography and map division"}, {"count": 7, "not": "https://www.loc.gov/search/?all=true&c=200&fa=partof!:cities+and+towns&fo=json&sb=shelf-id&sq=group:gmd.mar+AND+number_source_modified:%5B2021-10-07+TO+2021-10-08%5D", "off": null, "on": "https://www.loc.gov/search/?all=true&c=200&fa=partof:cities+and+towns&fo=json&sb=shelf-id&sq=group:gmd.mar+AND+number_source_modified:%5B2021-10-07+TO+2021-10-08%5D", "title": "cities and towns"}, {"count": 5, "not": "https://www.loc.gov/search/?all=true&c=200&fa=partof!:cultural+landscapes&fo=json&sb=shelf-id&sq=group:gmd.mar+AND+number_source_modified:%5B2021-10-07+TO+2021-10-08%5D", "off": null, "on": "https://www.loc.gov/search/?all=true&c=200&fa=partof:cultural+landscapes&fo=json&sb=shelf-id&sq=group:gmd.mar+AND+number_source_modified:%5B2021-10-07+TO+2021-10-08%5D", "title": "cultural landscapes"}, {"count": 1, "not": "https://www.loc.gov/search/?all=true&c=200&fa=partof!:county+landownership+maps&fo=json&sb=shelf-id&sq=group:gmd.mar+AND+number_source_modified:%5B2021-10-07+TO+2021-10-08%5D", "off": null, "on": "https://www.loc.gov/search/?all=true&c=200&fa=partof:county+landownership+maps&fo=json&sb=shelf-id&sq=group:gmd.mar+AND+number_source_modified:%5B2021-10-07+TO+2021-10-08%5D", "title": "county landownership maps"}, {"count": 1, "not": "https://www.loc.gov/search/?all=true&c=200&fa=partof!:general+maps&fo=json&sb=shelf-id&sq=group:gmd.mar+AND+number_source_modified:%5B2021-10-07+TO+2021-10-08%5D", "off": null, "on": "https://www.loc.gov/search/?all=true&c=200&fa=partof:general+maps&fo=json&sb=shelf-id&sq=group:gmd.mar+AND+number_source_modified:%5B2021-10-07+TO+2021-10-08%5D", "title": "general maps"}], "title": "Part of", "type": "partof"}, {"filters": [{"count": 5, "not": "https://www.loc.gov/search/?all=true&c=200&fa=contributor!:u.s.+coast+and+geodetic+survey&fo=json&sb=shelf-id&sq=group:gmd.mar+AND+number_source_modified:%5B2021-10-07+TO+2021-10-08%5D", "off": null, "on": "https://www.loc.gov/search/?all=true&c=200&fa=contributor:u.s.+coast+and+geodetic+survey&fo=json&sb=shelf-id&sq=group:gmd.mar+AND+number_source_modified:%5B2021-10-07+TO+2021-10-08%5D", "title": "u.s. coast and geodetic survey"}, {"count": 2, "not": "https://www.loc.gov/search/?all=true&c=200&fa=contributor!:totten,+john&fo=json&sb=shelf-id&sq=group:gmd.mar+AND+number_source_modified:%5B2021-10-07+TO+2021-10-08%5D", "off": null, "on": "https://www.loc.gov/search/?all=true&c=200&fa=contributor:totten,+john&fo=json&sb=shelf-id&sq=group:gmd.mar+AND+number_source_modified:%5B2021-10-07+TO+2021-10-08%5D", "title": "totten, john"}, {"count": 1, "not": "https://www.loc.gov/search/?all=true&c=200&fa=contributor!:e.+hexamer+%26+son&fo=json&sb=shelf-id&sq=group:gmd.mar+AND+number_source_modified:%5B2021-10-07+TO+2021-10-08%5D", "off": null, "on": "https://www.loc.gov/search/?all=true&c=200&fa=contributor:e.+hexamer+%26+son&fo=json&sb=shelf-id&sq=group:gmd.mar+AND+number_source_modified:%5B2021-10-07+TO+2021-10-08%5D", "title": "e. hexamer & son"}, {"count": 1, "not": "https://www.loc.gov/search/?all=true&c=200&fa=contributor!:garcia+y+solarer,+cristobal&fo=json&sb=shelf-id&sq=group:gmd.mar+AND+number_source_modified:%5B2021-10-07+TO+2021-10-08%5D", "off": null, "on": "https://www.loc.gov/search/?all=true&c=200&fa=contributor:garcia+y+solarer,+cristobal&fo=json&sb=shelf-id&sq=group:gmd.mar+AND+number_source_modified:%5B2021-10-07+TO+2021-10-08%5D", "title": "garcia y solarer, cristobal"}, {"count": 1, "not": "https://www.loc.gov/search/?all=true&c=200&fa=contributor!:hexamer,+ernest&fo=json&sb=shelf-id&sq=group:gmd.mar+AND+number_source_modified:%5B2021-10-07+TO+2021-10-08%5D", "off": null, "on": "https://www.loc.gov/search/?all=true&c=200&fa=contributor:hexamer,+ernest&fo=json&sb=shelf-id&sq=group:gmd.mar+AND+number_source_modified:%5B2021-10-07+TO+2021-10-08%5D", "title": "hexamer, ernest"}, {"count": 1, "not": "https://www.loc.gov/search/?all=true&c=200&fa=contributor!:locher,+william&fo=json&sb=shelf-id&sq=group:gmd.mar+AND+number_source_modified:%5B2021-10-07+TO+2021-10-08%5D", "off": null, "on": "https://www.loc.gov/search/?all=true&c=200&fa=contributor:locher,+william&fo=json&sb=shelf-id&sq=group:gmd.mar+AND+number_source_modified:%5B2021-10-07+TO+2021-10-08%5D", "title": "locher, william"}, {"count": 1, "not": "https://www.loc.gov/search/?all=true&c=200&fa=contributor!:rosales,+francisco&fo=json&sb=shelf-id&sq=group:gmd.mar+AND+number_source_modified:%5B2021-10-07+TO+2021-10-08%5D", "off": null, "on": "https://www.loc.gov/search/?all=true&c=200&fa=contributor:rosales,+francisco&fo=json&sb=shelf-id&sq=group:gmd.mar+AND+number_source_modified:%5B2021-10-07+TO+2021-10-08%5D", "title": "rosales, francisco"}, {"count": 1, "not": "https://www.loc.gov/search/?all=true&c=200&fa=contributor!:united+states.+national+park+service&fo=json&sb=shelf-id&sq=group:gmd.mar+AND+number_source_modified:%5B2021-10-07+TO+2021-10-08%5D", "off": null, "on": "https://www.loc.gov/search/?all=true&c=200&fa=contributor:united+states.+national+park+service&fo=json&sb=shelf-id&sq=group:gmd.mar+AND+number_source_modified:%5B2021-10-07+TO+2021-10-08%5D", "title": "united states. national park service"}, {"count": 1, "not": "https://www.loc.gov/search/?all=true&c=200&fa=contributor!:vanderbilt,+cornelius&fo=json&sb=shelf-id&sq=group:gmd.mar+AND+number_source_modified:%5B2021-10-07+TO+2021-10-08%5D", "off": null, "on": "https://www.loc.gov/search/?all=true&c=200&fa=contributor:vanderbilt,+cornelius&fo=json&sb=shelf-id&sq=group:gmd.mar+AND+number_source_modified:%5B2021-10-07+TO+2021-10-08%5D", "title": "vanderbilt, cornelius"}], "title": "Contributor", "type": "contributor"}, {"filters": [{"count": 8, "not": "https://www.loc.gov/search/?all=true&c=200&fa=subject!:maps&fo=json&sb=shelf-id&sq=group:gmd.mar+AND+number_source_modified:%5B2021-10-07+TO+2021-10-08%5D", "off": null, "on": "https://www.loc.gov/search/?all=true&c=200&fa=subject:maps&fo=json&sb=shelf-id&sq=group:gmd.mar+AND+number_source_modified:%5B2021-10-07+TO+2021-10-08%5D", "title": "maps"}, {"count": 7, "not": "https://www.loc.gov/search/?all=true&c=200&fa=subject!:united+states&fo=json&sb=shelf-id&sq=group:gmd.mar+AND+number_source_modified:%5B2021-10-07+TO+2021-10-08%5D", "off": null, "on": "https://www.loc.gov/search/?all=true&c=200&fa=subject:united+states&fo=json&sb=shelf-id&sq=group:gmd.mar+AND+number_source_modified:%5B2021-10-07+TO+2021-10-08%5D", "title": "united states"}, {"count": 6, "not": "https://www.loc.gov/search/?all=true&c=200&fa=subject!:manuscript+maps&fo=json&sb=shelf-id&sq=group:gmd.mar+AND+number_source_modified:%5B2021-10-07+TO+2021-10-08%5D", "off": null, "on": "https://www.loc.gov/search/?all=true&c=200&fa=subject:manuscript+maps&fo=json&sb=shelf-id&sq=group:gmd.mar+AND+number_source_modified:%5B2021-10-07+TO+2021-10-08%5D", "title": "manuscript maps"}, {"count": 5, "not": "https://www.loc.gov/search/?all=true&c=200&fa=subject!:cadastral+maps&fo=json&sb=shelf-id&sq=group:gmd.mar+AND+number_source_modified:%5B2021-10-07+TO+2021-10-08%5D", "off": null, "on": "https://www.loc.gov/search/?all=true&c=200&fa=subject:cadastral+maps&fo=json&sb=shelf-id&sq=group:gmd.mar+AND+number_source_modified:%5B2021-10-07+TO+2021-10-08%5D", "title": "cadastral maps"}, {"count": 5, "not": "https://www.loc.gov/search/?all=true&c=200&fa=subject!:landowners&fo=json&sb=shelf-id&sq=group:gmd.mar+AND+number_source_modified:%5B2021-10-07+TO+2021-10-08%5D", "off": null, "on": "https://www.loc.gov/search/?all=true&c=200&fa=subject:landowners&fo=json&sb=shelf-id&sq=group:gmd.mar+AND+number_source_modified:%5B2021-10-07+TO+2021-10-08%5D", "title": "landowners"}, {"count": 5, "not": "https://www.loc.gov/search/?all=true&c=200&fa=subject!:new+york&fo=json&sb=shelf-id&sq=group:gmd.mar+AND+number_source_modified:%5B2021-10-07+TO+2021-10-08%5D", "off": null, "on": "https://www.loc.gov/search/?all=true&c=200&fa=subject:new+york&fo=json&sb=shelf-id&sq=group:gmd.mar+AND+number_source_modified:%5B2021-10-07+TO+2021-10-08%5D", "title": "new york"}, {"count": 5, "not": "https://www.loc.gov/search/?all=true&c=200&fa=subject!:new+york+%28state%29&fo=json&sb=shelf-id&sq=group:gmd.mar+AND+number_source_modified:%5B2021-10-07+TO+2021-10-08%5D", "off": null, "on": "https://www.loc.gov/search/?all=true&c=200&fa=subject:new+york+%28state%29&fo=json&sb=shelf-id&sq=group:gmd.mar+AND+number_source_modified:%5B2021-10-07+TO+2021-10-08%5D", "title": "new york (state)"}, {"count": 5, "not": "https://www.loc.gov/search/?all=true&c=200&fa=subject!:staten+island&fo=json&sb=shelf-id&sq=group:gmd.mar+AND+number_source_modified:%5B2021-10-07+TO+2021-10-08%5D", "off": null, "on": "https://www.loc.gov/search/?all=true&c=200&fa=subject:staten+island&fo=json&sb=shelf-id&sq=group:gmd.mar+AND+number_source_modified:%5B2021-10-07+TO+2021-10-08%5D", "title": "staten island"}, {"count": 5, "not": "https://www.loc.gov/search/?all=true&c=200&fa=subject!:staten+island+%28new+york,+n.y.%29&fo=json&sb=shelf-id&sq=group:gmd.mar+AND+number_source_modified:%5B2021-10-07+TO+2021-10-08%5D", "off": null, "on": "https://www.loc.gov/search/?all=true&c=200&fa=subject:staten+island+%28new+york,+n.y.%29&fo=json&sb=shelf-id&sq=group:gmd.mar+AND+number_source_modified:%5B2021-10-07+TO+2021-10-08%5D", "title": "staten island (new york, n.y.)"}, {"count": 1, "not": "https://www.loc.gov/search/?all=true&c=200&fa=subject!:amecameca+region&fo=json&sb=shelf-id&sq=group:gmd.mar+AND+number_source_modified:%5B2021-10-07+TO+2021-10-08%5D", "off": null, "on": "https://www.loc.gov/search/?all=true&c=200&fa=subject:amecameca+region&fo=json&sb=shelf-id&sq=group:gmd.mar+AND+number_source_modified:%5B2021-10-07+TO+2021-10-08%5D", "title": "amecameca region"}], "index": "https://www.loc.gov/search/index/subject/?all=true&c=200&fo=json&sq=group:gmd.mar+AND+number_source_modified:%5B2021-10-07+TO+2021-10-08%5D", "title": "Subject", "type": "subject"}, {"filters": [{"count": 7, "not": "https://www.loc.gov/search/?all=true&c=200&fa=language!:english&fo=json&sb=shelf-id&sq=group:gmd.mar+AND+number_source_modified:%5B2021-10-07+TO+2021-10-08%5D", "off": null, "on": "https://www.loc.gov/search/?all=true&c=200&fa=language:english&fo=json&sb=shelf-id&sq=group:gmd.mar+AND+number_source_modified:%5B2021-10-07+TO+2021-10-08%5D", "title": "english"}, {"count": 1, "not": "https://www.loc.gov/search/?all=true&c=200&fa=language!:spanish&fo=json&sb=shelf-id&sq=group:gmd.mar+AND+number_source_modified:%5B2021-10-07+TO+2021-10-08%5D", "off": null, "on": "https://www.loc.gov/search/?all=true&c=200&fa=language:spanish&fo=json&sb=shelf-id&sq=group:gmd.mar+AND+number_source_modified:%5B2021-10-07+TO+2021-10-08%5D", "title": "spanish"}], "title": "Language", "type": "language"}, {"filters": [{"count": 8, "not": "https://www.loc.gov/search/?all=true&c=200&fa=access-restricted!:false&fo=json&sb=shelf-id&sq=group:gmd.mar+AND+number_source_modified:%5B2021-10-07+TO+2021-10-08%5D", "off": null, "on": "https://www.loc.gov/search/?all=true&c=200&fa=access-restricted:false&fo=json&sb=shelf-id&sq=group:gmd.mar+AND+number_source_modified:%5B2021-10-07+TO+2021-10-08%5D", "title": "false"}], "title": "Access Condition", "type": "access-restricted"}], "pagination": {"current": 1, "first": null, "from": 1, "last": null, "next": null, "of": 8, "page_list": [{"number": 1, "url": null}], "perpage": 200, "perpage_options": [25, 50, 100, 150], "previous": null, "results": "1 - 8", "to": 8, "total": 1}, "results": [{"access_restricted": false, "aka": ["http://www.loc.gov/resource/g3824pm.gla00443/", "http://www.loc.gov/resource/g3824pm.gla00442/", "http://www.loc.gov/item/2005633562/", "http://www.loc.gov/resource/g3824pm.gla00445/", "http://www.loc.gov/resource/g3824pm.gla00444/", "http://www.loc.gov/resource/g3824pm.gla00448/", "http://www.loc.gov/resource/g3824pm.gla00441/", "http://www.loc.gov/resource/g3824pm.gla00447/", "http://www.loc.gov/resource/g3824pm.gla00446/", "https://hdl.loc.gov/loc.gmd/g3824pm.gla00444", "https://hdl.loc.gov/loc.gmd/g3824pm.gla00445", "https://hdl.loc.gov/loc.gmd/g3824pm.gla00446", "https://hdl.loc.gov/loc.gmd/g3824pm.gla00447", "https://hdl.loc.gov/loc.gmd/g3824pm.gla00440", "https://hdl.loc.gov/loc.gmd/g3824pm.gla00441", "https://hdl.loc.gov/loc.gmd/g3824pm.gla00442", "https://hdl.loc.gov/loc.gmd/g3824pm.gla00443", "http://www.loc.gov/resource/g3824pm.gla00440/", "https://hdl.loc.gov/loc.gmd/g3824pm.gla00448", "http://lccn.loc.gov/2005633562"], "campaigns": [], "contributor": ["locher, william", "e. hexamer & son", "hexamer, ernest"], "date": "1857", "dates": ["1857-01-01T00:00:00Z"], "description": ["Some atlases surveyed by Ernest Hexamer & William Locher. Some atlases surveyed and drawn by Ernest Hexamer. Some atlases surveyed and drawn by Ernest Hexamer & Son. Orientation varies. Described in unpublished index to non-Sanborn fire insurance maps in Geography & Map Division Reading Room. Annotations in pencil and colored pencil on most maps. Amendments pasted on most maps. Available also through the Library of Congress Web site as a raster image. Check call number and author Cutter."], "digitized": true, "extract_timestamp": "2021-10-09T15:45:31.833Z", "group": ["gmd.mar", "catalog", "general-maps", "main-catalog"], "hassegments": true, "id": "http://www.loc.gov/item/2005633562/", "image_url": ["https://tile.loc.gov/storage-services/service/gmd/gmd382m/g3824m/g3824pm/gla00440/ca000001.gif", "https://tile.loc.gov/storage-services/service/gmd/gmd382m/g3824m/g3824pm/gla00440/ca000001.gif#h=150&w=99", "https://tile.loc.gov/image-services/iiif/service:gmd:gmd382m:g3824m:g3824pm:gla00440:ca000001/full/pct:12.5/0/default.jpg#h=1010&w=667", "https://tile.loc.gov/image-services/iiif/service:gmd:gmd382m:g3824m:g3824pm:gla00440:ca000001/full/pct:25/0/default.jpg#h=2020&w=1334"], "index": 1, "item": {"call_number": ["G1264.P5 H 1872"], "contents": ["vol. 1 <1857, 1872, 1890, 1892 (skeleton sheets), 1895, 1898, 1901, 1906, 1915> -- vol. 2. <1858, 1872, 1887, 1894, 1896, 1900, 1905, 1906, 1915> -- vol. 3. <1858, 1872, 1887, 1896, 1901, 1908> -- vol. 4. <1859, 1873 (2 copies), 1889, 1896, 1901, 1907> -- vol. 5. <1859, 1874, 1889, 1897, 1907> -- vol. 6 <1859, 1876, 1899, 1909> -- vol. 7 <1877, 1904> -- vol. 8 <1879, 1891, 1898, 1906> -- vol. 9 <1884, 1897, 1906> -- vol. 10 <1885, 1902, 1914> -- vol. 11 <1887, 1904> -- vol. 12 <1888, 1905> -- vol. 13 <1888, 1909> -- vol. 14 <1890> -- vol. 15 <1889, 1909> -- vol. 16 <1890, 1908> -- vol. 17 <1891, 1910> -- vol. 18 <1892> -- vol. 19 <1892, 1913> -- vol. 20 <1893, 1915> -- vol. 21 <1893, 1916> -- vol. 22 <1894, 1912> -- vol. 23 <1894> -- vol. 24 <1894> -- vol. 25 <1895, 1910> -- vol. 26 <1895> -- vol. 27 <1895> -- vol. 28 <1896, 1914> -- vol. 29 <1896> -- vol. 30 <1896> -- vol. 31 <1896 (2 copies)> -- vol. 32 <1897> -- vol. 33 <1898> -- vol. 34 <1907 (2 copies)> -- vol. 35 <1910 (2 copies)> -- vol. 36 <1910> -- vol. 37 <1911 (2 copies)> -- vol. 38 <1912>"], "contributors": ["E. Hexamer & Son.", "Hexamer, Ernest.", "Locher, William."], "created_published": ["Philadelphia : Ernest Hexamer & Son, <1857-1915>"], "date": "1857", "digital_id": ["https://hdl.loc.gov/loc.gmd/g3824pm.gla00440", "https://hdl.loc.gov/loc.gmd/g3824pm.gla00441", "https://hdl.loc.gov/loc.gmd/g3824pm.gla00442", "https://hdl.loc.gov/loc.gmd/g3824pm.gla00443", "https://hdl.loc.gov/loc.gmd/g3824pm.gla00444", "https://hdl.loc.gov/loc.gmd/g3824pm.gla00445", "https://hdl.loc.gov/loc.gmd/g3824pm.gla00446", "https://hdl.loc.gov/loc.gmd/g3824pm.gla00447", "https://hdl.loc.gov/loc.gmd/g3824pm.gla00448"], "format": ["cartographic"], "language": ["eng"], "location": ["Pennsylvania--Philadelphia", "Philadelphia (Pa.)"], "medium": ["atlases (v. <1-38>) : col. maps (some hand col.), some mounted on cloth ; 70 cm."], "notes": ["Some atlases surveyed by Ernest Hexamer & William Locher.", "Some atlases surveyed and drawn by Ernest Hexamer.", "Some atlases surveyed and drawn by Ernest Hexamer & Son.", "Orientation varies.", "Described in unpublished index to non-Sanborn fire insurance maps in Geography & Map Division Reading Room.", "Annotations in pencil and colored pencil on most maps. Amendments pasted on most maps.", "Available also through the Library of Congress Web site as a raster image.", "Check call number and author Cutter."], "number_former_id": ["https://www.loc.gov/item/2005633562", "https://www.loc.gov/item/5825476"], "other_title": ["Maps of the city of Philadelphia", "Insurance maps of the suburbs of Philadelphia", "Insurance maps, suburbs of Philadelphia"], "repository": ["Library of Congress Geography and Map Division Washington, D.C. 20540-4650 USA dcu"], "subjects": ["Philadelphia (Pa.)--Maps", "Real property--Pennsylvania--Philadelphia--Maps", "Fire insurance--Pennsylvania--Philadelphia--Maps", "United States--Pennsylvania--Philadelphia"], "title": "Insurance maps of the city of Philadelphia."}, "language": ["english"], "location": ["pennsylvania", "united states", "philadelphia"], "location_city": ["philadelphia"], "location_country": ["united states"], "location_state": ["pennsylvania"], "mime_type": ["image/gif", "image/tiff", "image/jpeg", "image/jp2"], "number": ["2021-10-07t10:14:33", "http://www.loc.gov/item/2005633562", "2005633562", "http://www.loc.gov/item/5825476"], "number_former_id": ["http://www.loc.gov/item/2005633562", "http://www.loc.gov/item/5825476"], "number_lccn": ["2005633562"], "number_source_modified": ["2021-10-07t10:14:33"], "online_format": ["image"], "original_format": ["map"], "other_title": ["Maps of the city of Philadelphia", "Insurance maps of the suburbs of Philadelphia", "Insurance maps, suburbs of Philadelphia"], "partof": ["american memory", "cities and towns", "catalog", "county landownership maps", "geography and map division"], "resources": [{"caption": "Vol. 1 1872", "captions": "https://tile.loc.gov/storage-services/service/gmd/gmd382m/g3824m/g3824pm/gla00440/captions.txt", "files": 16, "image": "https://tile.loc.gov/storage-services/service/gmd/gmd382m/g3824m/g3824pm/gla00440/ca000001.gif", "search": "https://www.loc.gov/search/?all=true&c=200&fa=segmentof:g3824pm.gla00440/&fo=json&sb=shelf-id&sq=group:gmd.mar+AND+number_source_modified:%5B2021-10-07+TO+2021-10-08%5D&st=gallery", "segments": 16, "url": "https://www.loc.gov/resource/g3824pm.gla00440/"}, {"caption": "Vol. 1 1890", "captions": "https://tile.loc.gov/storage-services/service/gmd/gmd382m/g3824m/g3824pm/gla00441/captions.txt", "files": 16, "image": "https://tile.loc.gov/storage-services/service/gmd/gmd382m/g3824m/g3824pm/gla00441/ca000001.gif", "search": "https://www.loc.gov/search/?all=true&c=200&fa=segmentof:g3824pm.gla00441/&fo=json&sb=shelf-id&sq=group:gmd.mar+AND+number_source_modified:%5B2021-10-07+TO+2021-10-08%5D&st=gallery", "segments": 16, "url": "https://www.loc.gov/resource/g3824pm.gla00441/"}, {"caption": "Vol. 1 1892", "captions": "https://tile.loc.gov/storage-services/service/gmd/gmd382m/g3824m/g3824pm/gla00442/captions.txt", "files": 14, "image": "https://tile.loc.gov/storage-services/service/gmd/gmd382m/g3824m/g3824pm/gla00442/ca000001.gif", "search": "https://www.loc.gov/search/?all=true&c=200&fa=segmentof:g3824pm.gla00442/&fo=json&sb=shelf-id&sq=group:gmd.mar+AND+number_source_modified:%5B2021-10-07+TO+2021-10-08%5D&st=gallery", "segments": 14, "url": "https://www.loc.gov/resource/g3824pm.gla00442/"}, {"caption": "Vol. 1 1895", "files": 16, "image": "https://tile.loc.gov/storage-services/service/gmd/gmd382m/g3824m/g3824pm/gla00443/ca000001.gif", "search": "https://www.loc.gov/search/?all=true&c=200&fa=segmentof:g3824pm.gla00443/&fo=json&sb=shelf-id&sq=group:gmd.mar+AND+number_source_modified:%5B2021-10-07+TO+2021-10-08%5D&st=gallery", "segments": 16, "url": "https://www.loc.gov/resource/g3824pm.gla00443/"}, {"caption": "Vol. 1 1897", "files": 54, "image": "https://tile.loc.gov/storage-services/service/gmd/gmd382m/g3824m/g3824pm/gla00444/ca000001.gif", "search": "https://www.loc.gov/search/?all=true&c=200&fa=segmentof:g3824pm.gla00444/&fo=json&sb=shelf-id&sq=group:gmd.mar+AND+number_source_modified:%5B2021-10-07+TO+2021-10-08%5D&st=gallery", "segments": 54, "url": "https://www.loc.gov/resource/g3824pm.gla00444/"}, {"caption": "Vol. 1 1898", "files": 50, "image": "https://tile.loc.gov/storage-services/service/gmd/gmd382m/g3824m/g3824pm/gla00445/ca000001.gif", "search": "https://www.loc.gov/search/?all=true&c=200&fa=segmentof:g3824pm.gla00445/&fo=json&sb=shelf-id&sq=group:gmd.mar+AND+number_source_modified:%5B2021-10-07+TO+2021-10-08%5D&st=gallery", "segments": 50, "url": "https://www.loc.gov/resource/g3824pm.gla00445/"}, {"caption": "Vol. 1 1901", "captions": "https://tile.loc.gov/storage-services/service/gmd/gmd382m/g3824m/g3824pm/gla00446/captions.txt", "files": 57, "image": "https://tile.loc.gov/storage-services/service/gmd/gmd382m/g3824m/g3824pm/gla00446/ca000001.gif", "search": "https://www.loc.gov/search/?all=true&c=200&fa=segmentof:g3824pm.gla00446/&fo=json&sb=shelf-id&sq=group:gmd.mar+AND+number_source_modified:%5B2021-10-07+TO+2021-10-08%5D&st=gallery", "segments": 57, "url": "https://www.loc.gov/resource/g3824pm.gla00446/"}, {"caption": "Vol. 1 1906", "captions": "https://tile.loc.gov/storage-services/service/gmd/gmd382m/g3824m/g3824pm/gla00447/captions.txt", "files": 55, "image": "https://tile.loc.gov/storage-services/service/gmd/gmd382m/g3824m/g3824pm/gla00447/ca000001.gif", "search": "https://www.loc.gov/search/?all=true&c=200&fa=segmentof:g3824pm.gla00447/&fo=json&sb=shelf-id&sq=group:gmd.mar+AND+number_source_modified:%5B2021-10-07+TO+2021-10-08%5D&st=gallery", "segments": 55, "url": "https://www.loc.gov/resource/g3824pm.gla00447/"}, {"caption": "Vol. 1 1915", "captions": "https://tile.loc.gov/storage-services/service/gmd/gmd382m/g3824m/g3824pm/gla00448/captions.txt", "files": 55, "image": "https://tile.loc.gov/storage-services/service/gmd/gmd382m/g3824m/g3824pm/gla00448/ca000001.gif", "search": "https://www.loc.gov/search/?all=true&c=200&fa=segmentof:g3824pm.gla00448/&fo=json&sb=shelf-id&sq=group:gmd.mar+AND+number_source_modified:%5B2021-10-07+TO+2021-10-08%5D&st=gallery", "segments": 55, "url": "https://www.loc.gov/resource/g3824pm.gla00448/"}], "segments": [{"count": 16, "link": "https://www.loc.gov/search/?all=true&c=200&fa=segmentof:g3824pm.gla00443/&fo=json&sb=shelf-id&sq=group:gmd.mar+AND+number_source_modified:%5B2021-10-07+TO+2021-10-08%5D&st=gallery", "url": "https://www.loc.gov/resource/g3824pm.gla00443/"}, {"count": 14, "link": "https://www.loc.gov/search/?all=true&c=200&fa=segmentof:g3824pm.gla00442/&fo=json&sb=shelf-id&sq=group:gmd.mar+AND+number_source_modified:%5B2021-10-07+TO+2021-10-08%5D&st=gallery", "url": "https://www.loc.gov/resource/g3824pm.gla00442/"}, {"count": 16, "link": "https://www.loc.gov/search/?all=true&c=200&fa=segmentof:g3824pm.gla00440/&fo=json&sb=shelf-id&sq=group:gmd.mar+AND+number_source_modified:%5B2021-10-07+TO+2021-10-08%5D&st=gallery", "url": "https://www.loc.gov/resource/g3824pm.gla00440/"}, {"count": 16, "link": "https://www.loc.gov/search/?all=true&c=200&fa=segmentof:g3824pm.gla00441/&fo=json&sb=shelf-id&sq=group:gmd.mar+AND+number_source_modified:%5B2021-10-07+TO+2021-10-08%5D&st=gallery", "url": "https://www.loc.gov/resource/g3824pm.gla00441/"}, {"count": 55, "link": "https://www.loc.gov/search/?all=true&c=200&fa=segmentof:g3824pm.gla00447/&fo=json&sb=shelf-id&sq=group:gmd.mar+AND+number_source_modified:%5B2021-10-07+TO+2021-10-08%5D&st=gallery", "url": "https://www.loc.gov/resource/g3824pm.gla00447/"}, {"count": 57, "link": "https://www.loc.gov/search/?all=true&c=200&fa=segmentof:g3824pm.gla00446/&fo=json&sb=shelf-id&sq=group:gmd.mar+AND+number_source_modified:%5B2021-10-07+TO+2021-10-08%5D&st=gallery", "url": "https://www.loc.gov/resource/g3824pm.gla00446/"}, {"count": 54, "link": "https://www.loc.gov/search/?all=true&c=200&fa=segmentof:g3824pm.gla00444/&fo=json&sb=shelf-id&sq=group:gmd.mar+AND+number_source_modified:%5B2021-10-07+TO+2021-10-08%5D&st=gallery", "url": "https://www.loc.gov/resource/g3824pm.gla00444/"}, {"count": 50, "link": "https://www.loc.gov/search/?all=true&c=200&fa=segmentof:g3824pm.gla00445/&fo=json&sb=shelf-id&sq=group:gmd.mar+AND+number_source_modified:%5B2021-10-07+TO+2021-10-08%5D&st=gallery", "url": "https://www.loc.gov/resource/g3824pm.gla00445/"}, {"count": 55, "link": "https://www.loc.gov/search/?all=true&c=200&fa=segmentof:g3824pm.gla00448/&fo=json&sb=shelf-id&sq=group:gmd.mar+AND+number_source_modified:%5B2021-10-07+TO+2021-10-08%5D&st=gallery", "url": "https://www.loc.gov/resource/g3824pm.gla00448/"}], "shelf_id": "G1264.P5 H 1872", "site": ["ammem", "catalog"], "subject": ["pennsylvania", "philadelphia (pa.)", "philadelphia", "united states", "maps", "real property", "fire insurance"], "timestamp": "2021-10-09T15:46:23.267Z", "title": "Insurance maps of the city of Philadelphia.", "url": "https://www.loc.gov/item/2005633562/"}, {"access_restricted": false, "aka": ["http://www.loc.gov/item/2021590560/", "http://www.loc.gov/resource/g3804n.ct005754/", "https://hdl.loc.gov/loc.gmd/g3804n.ct005754", "http://lccn.loc.gov/2021590560"], "campaigns": [], "contributor": ["u.s. coast and geodetic survey", "vanderbilt, cornelius"], "date": "1818", "dates": ["1818-01-01T00:00:00Z"], "description": ["A manuscript copy of a manuscript original. Pen-and-ink on tracing linen, mounted on cloth. In ink in another hand: grant 14 April 1818. Includes notes. In pen and ink on octagonal blue bordered label in lower right corner: 851 n 53 1818. Transferred from the USCGS January 15, 1914. Available also through the Library of Congress Web site as a raster image."], "digitized": true, "extract_timestamp": "2021-10-09T15:45:31.833Z", "group": ["gmd.mar", "catalog", "general-maps", "main-catalog"], "hassegments": false, "id": "http://www.loc.gov/item/2021590560/", "image_url": ["https://tile.loc.gov/storage-services/service/gmd/gmd380/g3804/g3804n/ct005754.gif", "https://tile.loc.gov/storage-services/service/gmd/gmd380/g3804/g3804n/ct005754.gif#h=150&w=104", "https://tile.loc.gov/image-services/iiif/service:gmd:gmd380:g3804:g3804n:ct005754/full/pct:12.5/0/default.jpg#h=514&w=356", "https://tile.loc.gov/image-services/iiif/service:gmd:gmd380:g3804:g3804n:ct005754/full/pct:25/0/default.jpg#h=1028&w=713"], "index": 2, "item": {"call_number": ["G3804.N4:2S8G46 1818 .R5"], "contributors": ["Vanderbilt, Cornelius, 1794-1877, landowner.", "U.S. Coast and Geodetic Survey, former owner."], "created_published": ["[between 1860 and 1900?]"], "date": "1818", "digital_id": ["https://hdl.loc.gov/loc.gmd/g3804n.ct005754"], "format": ["cartographic"], "genre": ["Manuscript maps", "Cadastral maps"], "language": ["eng"], "location": ["New York (State)--New York", "Staten Island (New York, N.Y.)"], "medium": ["1 manuscript map : cloth ; 20 x 9 cm, on sheet 34 x 22 cm"], "notes": ["A manuscript copy of a manuscript original.", "Pen-and-ink on tracing linen, mounted on cloth.", "In ink in another hand: grant 14 April 1818.", "Includes notes.", "In pen and ink on octagonal blue bordered label in lower right corner: 851 n 53 1818.", "Transferred from the USCGS January 15, 1914.", "Available also through the Library of Congress Web site as a raster image."], "number_former_id": ["https://www.loc.gov/item/2021590560", "https://www.loc.gov/item/22249687"], "repository": ["Library of Congress Geography and Map Division Washington, D.C. 20540-4650 USA dcu"], "subjects": ["Landowners--New York (State)--New York--Maps", "Staten Island (New York, N.Y.)--Maps", "United States--New York (State)--New York--Staten Island"], "title": "Richmond County, February 16th 1818 : the annexed is a map of land under water in front of land of Cornelius Vanderbilt and land of John Deforest."}, "language": ["english"], "location": ["united states", "new york", "new york (state)", "staten island"], "location_city": ["new york"], "location_country": ["united states"], "location_state": ["new york (state)"], "mime_type": ["image/gif", "image/tiff", "image/jpeg", "image/jp2"], "number": ["http://www.loc.gov/item/2021590560", "2021-10-07t13:04:26", "sheet", "http://www.loc.gov/item/22249687", "2021590560"], "number_carrier_type": ["sheet"], "number_former_id": ["http://www.loc.gov/item/2021590560", "http://www.loc.gov/item/22249687"], "number_lccn": ["2021590560"], "number_source_modified": ["2021-10-07t13:04:26"], "online_format": ["image"], "original_format": ["map"], "other_title": [], "partof": ["american memory", "cities and towns", "catalog", "geography and map division", "cultural landscapes"], "resources": [{"files": 1, "image": "https://tile.loc.gov/storage-services/service/gmd/gmd380/g3804/g3804n/ct005754.gif", "url": "https://www.loc.gov/resource/g3804n.ct005754/"}], "shelf_id": "G3804.N4:2S8G46 1818 .R5", "site": ["ammem", "catalog"], "subject": ["cadastral maps", "staten island", "united states", "maps", "new york", "staten island (new york, n.y.)", "new york (state)", "landowners", "manuscript maps"], "timestamp": "2021-10-09T15:46:23.267Z", "title": "Richmond County, February 16th 1818 : the annexed is a map of land under water in front of land of Cornelius Vanderbilt and land of John Deforest.", "url": "https://www.loc.gov/item/2021590560/"}, {"access_restricted": false, "aka": ["http://www.loc.gov/item/2021590554/", "http://www.loc.gov/resource/g3804n.ct005748/", "https://hdl.loc.gov/loc.gmd/g3804n.ct005748", "http://lccn.loc.gov/2021590554"], "campaigns": [], "contributor": ["u.s. coast and geodetic survey", "totten, john"], "date": "1824", "dates": ["1824-01-01T00:00:00Z"], "description": ["A manuscript copy of a manuscript original. Pen-and-ink and pencil on tracing linen. In ink in another hand: Grant 12 April 1825. Oriented with north to the bottom. In pen and ink on octagonal blue bordered label in lower right corner: 851 1825. Transferred from the USCGS January 15, 1914. Available also through the Library of Congress Web site as a raster image."], "digitized": true, "extract_timestamp": "2021-10-09T15:45:31.833Z", "group": ["gmd.mar", "catalog", "general-maps", "main-catalog"], "hassegments": false, "id": "http://www.loc.gov/item/2021590554/", "image_url": ["https://tile.loc.gov/storage-services/service/gmd/gmd380/g3804/g3804n/ct005748.gif", "https://tile.loc.gov/storage-services/service/gmd/gmd380/g3804/g3804n/ct005748.gif#h=150&w=87", "https://tile.loc.gov/image-services/iiif/service:gmd:gmd380:g3804:g3804n:ct005748/full/pct:12.5/0/default.jpg#h=602&w=348", "https://tile.loc.gov/image-services/iiif/service:gmd:gmd380:g3804:g3804n:ct005748/full/pct:25/0/default.jpg#h=1205&w=697"], "index": 3, "item": {"call_number": ["G3804.N4:2S8G46 1824 .T6"], "contributors": ["Totten, John, active 1824-1831, cartographer, surveyor.", "U.S. Coast and Geodetic Survey, former owner."], "created_published": ["[between 1860 and 1900?]"], "date": "1824", "digital_id": ["https://hdl.loc.gov/loc.gmd/g3804n.ct005748"], "format": ["cartographic"], "genre": ["Manuscript maps", "Cadastral maps"], "language": ["eng"], "location": ["New York (State)--New York", "Staten Island (New York, N.Y.)"], "medium": ["1 manuscript map : cloth ; 35 x 16 cm"], "notes": ["A manuscript copy of a manuscript original.", "Pen-and-ink and pencil on tracing linen.", "In ink in another hand: Grant 12 April 1825.", "Oriented with north to the bottom.", "In pen and ink on octagonal blue bordered label in lower right corner: 851 1825.", "Transferred from the USCGS January 15, 1914.", "Available also through the Library of Congress Web site as a raster image."], "number_former_id": ["https://www.loc.gov/item/2021590554", "https://www.loc.gov/item/22249396"], "repository": ["Library of Congress Geography and Map Division Washington, D.C. 20540-4650 USA dcu"], "subjects": ["Landowners--New York (State)--New York--Maps", "Staten Island (New York, N.Y.)--Maps", "United States--New York (State)--New York--Staten Island"], "title": "Map of the land of Joseph Seguine : [Staten Island, New York]"}, "language": ["english"], "location": ["united states", "new york", "new york (state)", "staten island"], "location_city": ["new york"], "location_country": ["united states"], "location_state": ["new york (state)"], "mime_type": ["image/gif", "image/tiff", "image/jpeg", "image/jp2"], "number": ["2021-10-07t13:05:29", "http://www.loc.gov/item/2021590554", "2021590554", "sheet", "http://www.loc.gov/item/22249396"], "number_carrier_type": ["sheet"], "number_former_id": ["http://www.loc.gov/item/2021590554", "http://www.loc.gov/item/22249396"], "number_lccn": ["2021590554"], "number_source_modified": ["2021-10-07t13:05:29"], "online_format": ["image"], "original_format": ["map"], "other_title": [], "partof": ["american memory", "cities and towns", "catalog", "geography and map division", "cultural landscapes"], "resources": [{"files": 1, "image": "https://tile.loc.gov/storage-services/service/gmd/gmd380/g3804/g3804n/ct005748.gif", "url": "https://www.loc.gov/resource/g3804n.ct005748/"}], "shelf_id": "G3804.N4:2S8G46 1824 .T6", "site": ["ammem", "catalog"], "subject": ["cadastral maps", "staten island", "united states", "maps", "new york", "staten island (new york, n.y.)", "new york (state)", "landowners", "manuscript maps"], "timestamp": "2021-10-09T15:46:23.267Z", "title": "Map of the land of Joseph Seguine : [Staten Island, New York]", "url": "https://www.loc.gov/item/2021590554/"}, {"access_restricted": false, "aka": ["https://hdl.loc.gov/loc.gmd/g3804n.ct005752", "http://www.loc.gov/item/2021590558/", "http://www.loc.gov/resource/g3804n.ct005752/", "http://lccn.loc.gov/2021590558"], "campaigns": [], "contributor": ["u.s. coast and geodetic survey", "totten, john"], "date": "1831", "dates": ["1831-01-01T00:00:00Z"], "description": ["Shows area adjacent to Staten Island. A manuscript copy of a manuscript original. Pen-and-ink on tracing linen. Includes notes. In pencil in different hand: No grant found to correspond with this map. In pen and ink on octagonal blue bordered label in lower right corner: 851 n. 53 1831. Transferred from the USCGS January 15, 1914. Available also through the Library of Congress Web site as a raster image."], "digitized": true, "extract_timestamp": "2021-10-09T15:45:31.833Z", "group": ["gmd.mar", "catalog", "general-maps", "main-catalog"], "hassegments": false, "id": "http://www.loc.gov/item/2021590558/", "image_url": ["https://tile.loc.gov/storage-services/service/gmd/gmd380/g3804/g3804n/ct005752.gif", "https://tile.loc.gov/storage-services/service/gmd/gmd380/g3804/g3804n/ct005752.gif#h=150&w=136", "https://tile.loc.gov/image-services/iiif/service:gmd:gmd380:g3804:g3804n:ct005752/full/pct:12.5/0/default.jpg#h=574&w=520", "https://tile.loc.gov/image-services/iiif/service:gmd:gmd380:g3804:g3804n:ct005752/full/pct:25/0/default.jpg#h=1149&w=1040"], "index": 4, "item": {"call_number": ["G3804.N4:2S8G46 1831 .T6"], "contributors": ["Totten, John, active 1824-1831, cartographer, surveyor.", "U.S. Coast and Geodetic Survey, former owner."], "created_published": ["[between 1860 and 1900?]"], "date": "1831", "digital_id": ["https://hdl.loc.gov/loc.gmd/g3804n.ct005752"], "format": ["cartographic"], "genre": ["Manuscript maps", "Cadastral maps"], "language": ["eng"], "location": ["New York (State)--New York", "Staten Island (New York, N.Y.)"], "medium": ["1 manuscript map : cloth ; 32 x 35 cm"], "notes": ["Shows area adjacent to Staten Island.", "A manuscript copy of a manuscript original.", "Pen-and-ink on tracing linen.", "Includes notes.", "In pencil in different hand: No grant found to correspond with this map.", "In pen and ink on octagonal blue bordered label in lower right corner: 851 n. 53 1831.", "Transferred from the USCGS January 15, 1914.", "Available also through the Library of Congress Web site as a raster image."], "number_former_id": ["https://www.loc.gov/item/2021590558", "https://www.loc.gov/item/22242386"], "repository": ["Library of Congress Geography and Map Division Washington, D.C. 20540-4650 USA dcu"], "subjects": ["Landowners--New York (State)--New York--Maps", "Staten Island (New York, N.Y.)--Maps", "United States--New York (State)--New York", "United States--New York (State)--New York--Staten Island"], "title": "Survey and map of the lands under water in front of the farm of Jasper Terry : [Staten Island, New York]"}, "language": ["english"], "location": ["united states", "new york", "new york (state)", "staten island"], "location_city": ["new york"], "location_country": ["united states"], "location_state": ["new york (state)"], "mime_type": ["image/gif", "image/tiff", "image/jpeg", "image/jp2"], "number": ["http://www.loc.gov/item/22242386", "2021-10-07t13:05:08", "sheet", "http://www.loc.gov/item/2021590558", "2021590558"], "number_carrier_type": ["sheet"], "number_former_id": ["http://www.loc.gov/item/2021590558", "http://www.loc.gov/item/22242386"], "number_lccn": ["2021590558"], "number_source_modified": ["2021-10-07t13:05:08"], "online_format": ["image"], "original_format": ["map"], "other_title": [], "partof": ["american memory", "cities and towns", "catalog", "geography and map division", "cultural landscapes"], "resources": [{"files": 1, "image": "https://tile.loc.gov/storage-services/service/gmd/gmd380/g3804/g3804n/ct005752.gif", "url": "https://www.loc.gov/resource/g3804n.ct005752/"}], "shelf_id": "G3804.N4:2S8G46 1831 .T6", "site": ["ammem", "catalog"], "subject": ["cadastral maps", "staten island", "united states", "maps", "new york", "staten island (new york, n.y.)", "new york (state)", "landowners", "manuscript maps"], "timestamp": "2021-10-09T15:46:23.267Z", "title": "Survey and map of the lands under water in front of the farm of Jasper Terry : [Staten Island, New York]", "url": "https://www.loc.gov/item/2021590558/"}, {"access_restricted": false, "aka": ["http://www.loc.gov/item/2021590555/", "http://www.loc.gov/resource/g3804n.ct005749/", "https://hdl.loc.gov/loc.gmd/g3804n.ct005749", "http://lccn.loc.gov/2021590555"], "campaigns": [], "contributor": ["u.s. coast and geodetic survey"], "date": "1837", "dates": ["1837-01-01T00:00:00Z"], "description": ["A manuscript copy of a manuscript original. Pen-and-ink and watercolor on tracing linen. \"Water grant Mar 1 1837\". Includes notes. In pen and ink on octagonal blue bordered label in lower right corner: 851 R 53 1837. Transferred from the USCGS January 15, 1914. Available also through the Library of Congress Web site as a raster image."], "digitized": true, "extract_timestamp": "2021-10-09T15:45:31.833Z", "group": ["gmd.mar", "catalog", "general-maps", "main-catalog"], "hassegments": false, "id": "http://www.loc.gov/item/2021590555/", "image_url": ["https://tile.loc.gov/storage-services/service/gmd/gmd380/g3804/g3804n/ct005749.gif", "https://tile.loc.gov/storage-services/service/gmd/gmd380/g3804/g3804n/ct005749.gif#h=111&w=150", "https://tile.loc.gov/image-services/iiif/service:gmd:gmd380:g3804:g3804n:ct005749/full/pct:12.5/0/default.jpg#h=860&w=1161", "https://tile.loc.gov/image-services/iiif/service:gmd:gmd380:g3804:g3804n:ct005749/full/pct:25/0/default.jpg#h=1721&w=2322"], "index": 5, "item": {"call_number": ["G3804.N4:2S8G46 1837 .J6"], "contributors": ["U.S. Coast and Geodetic Survey, former owner."], "created_published": ["[between 1860 and 1900?]"], "date": "1837", "digital_id": ["https://hdl.loc.gov/loc.gmd/g3804n.ct005749"], "format": ["cartographic"], "genre": ["Manuscript maps", "Cadastral maps"], "language": ["eng"], "location": ["New York (State)--New York", "Staten Island (New York, N.Y.)"], "medium": ["1 manuscript map : cloth, color ; 51 x 73 cm"], "notes": ["A manuscript copy of a manuscript original.", "Pen-and-ink and watercolor on tracing linen.", "\"Water grant Mar 1 1837\".", "Includes notes.", "In pen and ink on octagonal blue bordered label in lower right corner: 851 R 53 1837.", "Transferred from the USCGS January 15, 1914.", "Available also through the Library of Congress Web site as a raster image."], "number_former_id": ["https://www.loc.gov/item/2021590555", "https://www.loc.gov/item/22242530"], "repository": ["Library of Congress Geography and Map Division Washington, D.C. 20540-4650 USA dcu"], "subjects": ["Landowners--New York (State)--New York--Maps", "Staten Island (New York, N.Y.)--Maps", "United States--New York (State)--New York", "United States--New York (State)--New York--Staten Island"], "title": "Joseph H Seguine's lands in Westfield, Richmond County : [Staten Island, New York]."}, "language": ["english"], "location": ["united states", "new york", "new york (state)", "staten island"], "location_city": ["new york"], "location_country": ["united states"], "location_state": ["new york (state)"], "mime_type": ["image/gif", "image/tiff", "image/jpeg", "image/jp2"], "number": ["http://www.loc.gov/item/2021590555", "2021590555", "http://www.loc.gov/item/22242530", "sheet", "2021-10-07t12:59:28"], "number_carrier_type": ["sheet"], "number_former_id": ["http://www.loc.gov/item/2021590555", "http://www.loc.gov/item/22242530"], "number_lccn": ["2021590555"], "number_source_modified": ["2021-10-07t12:59:28"], "online_format": ["image"], "original_format": ["map"], "other_title": [], "partof": ["american memory", "cities and towns", "catalog", "geography and map division", "cultural landscapes"], "resources": [{"files": 1, "image": "https://tile.loc.gov/storage-services/service/gmd/gmd380/g3804/g3804n/ct005749.gif", "url": "https://www.loc.gov/resource/g3804n.ct005749/"}], "shelf_id": "G3804.N4:2S8G46 1837 .J6", "site": ["ammem", "catalog"], "subject": ["cadastral maps", "staten island", "united states", "maps", "new york", "staten island (new york, n.y.)", "new york (state)", "landowners", "manuscript maps"], "timestamp": "2021-10-09T15:46:23.267Z", "title": "Joseph H Seguine's lands in Westfield, Richmond County : [Staten Island, New York].", "url": "https://www.loc.gov/item/2021590555/"}, {"access_restricted": false, "aka": ["https://hdl.loc.gov/loc.gmd/g3804n.ct005750", "http://www.loc.gov/item/2021590556/", "http://www.loc.gov/resource/g3804n.ct005750/", "http://lccn.loc.gov/2021590556"], "campaigns": [], "contributor": ["u.s. coast and geodetic survey"], "date": "1839", "dates": ["1839-01-01T00:00:00Z"], "description": ["A manuscript copy of a manuscript original. Pen-and-ink. Oriented with north to the bottom. In ink in different hand under title: water grant Mar 6 1839. In pen and ink on octagonal blue bordered label in lower right corner: 851 1839. Transferred from the USCGS January 15, 1914. Available also through the Library of Congress Web site as a raster image."], "digitized": true, "extract_timestamp": "2021-10-09T15:45:31.833Z", "group": ["gmd.mar", "catalog", "general-maps", "main-catalog"], "hassegments": false, "id": "http://www.loc.gov/item/2021590556/", "image_url": ["https://tile.loc.gov/storage-services/service/gmd/gmd380/g3804/g3804n/ct005750.gif", "https://tile.loc.gov/storage-services/service/gmd/gmd380/g3804/g3804n/ct005750.gif#h=93&w=150", "https://tile.loc.gov/image-services/iiif/service:gmd:gmd380:g3804:g3804n:ct005750/full/pct:12.5/0/default.jpg#h=561&w=903", "https://tile.loc.gov/image-services/iiif/service:gmd:gmd380:g3804:g3804n:ct005750/full/pct:25/0/default.jpg#h=1123&w=1806"], "index": 6, "item": {"call_number": ["G3804.N4:2S8G46 1839 .M3"], "contributors": ["U.S. Coast and Geodetic Survey, former owner."], "created_published": ["[between 1860 and 1900?]"], "date": "1839", "digital_id": ["https://hdl.loc.gov/loc.gmd/g3804n.ct005750"], "format": ["cartographic"], "genre": ["Manuscript maps", "Cadastral maps"], "language": ["eng"], "location": ["New York (State)--New York", "Staten Island (New York, N.Y.)"], "medium": ["1 manuscript map : cloth ; 37 x 56 cm"], "notes": ["A manuscript copy of a manuscript original.", "Pen-and-ink.", "Oriented with north to the bottom.", "In ink in different hand under title: water grant Mar 6 1839.", "In pen and ink on octagonal blue bordered label in lower right corner: 851 1839.", "Transferred from the USCGS January 15, 1914.", "Available also through the Library of Congress Web site as a raster image."], "number_former_id": ["https://www.loc.gov/item/2021590556", "https://www.loc.gov/item/22242513"], "repository": ["Library of Congress Geography and Map Division Washington, D.C. 20540-4650 USA dcu"], "subjects": ["Landowners--New York (State)--New York--Maps", "Staten Island (New York, N.Y.)--Maps", "United States--New York (State)--New York", "United States--New York (State)--New York--Staten Island"], "title": "Map of the land of Dr J T Harrison : [Staten Island, New York]."}, "language": ["english"], "location": ["united states", "new york", "new york (state)", "staten island"], "location_city": ["new york"], "location_country": ["united states"], "location_state": ["new york (state)"], "mime_type": ["image/gif", "image/tiff", "image/jpeg", "image/jp2"], "number": ["2021590556", "http://www.loc.gov/item/2021590556", "sheet", "http://www.loc.gov/item/22242513", "2021-10-07t13:03:48"], "number_carrier_type": ["sheet"], "number_former_id": ["http://www.loc.gov/item/2021590556", "http://www.loc.gov/item/22242513"], "number_lccn": ["2021590556"], "number_source_modified": ["2021-10-07t13:03:48"], "online_format": ["image"], "original_format": ["map"], "other_title": [], "partof": ["american memory", "cities and towns", "catalog", "geography and map division", "cultural landscapes"], "resources": [{"files": 1, "image": "https://tile.loc.gov/storage-services/service/gmd/gmd380/g3804/g3804n/ct005750.gif", "url": "https://www.loc.gov/resource/g3804n.ct005750/"}], "shelf_id": "G3804.N4:2S8G46 1839 .M3", "site": ["ammem", "catalog"], "subject": ["cadastral maps", "staten island", "united states", "maps", "new york", "staten island (new york, n.y.)", "new york (state)", "landowners", "manuscript maps"], "timestamp": "2021-10-09T15:46:23.267Z", "title": "Map of the land of Dr J T Harrison : [Staten Island, New York].", "url": "https://www.loc.gov/item/2021590556/"}, {"access_restricted": false, "aka": ["http://www.loc.gov/item/2008622210/", "https://hdl.loc.gov/loc.gmd/g4082h.ct011881", "http://www.loc.gov/resource/g4082h.ct011881/", "http://lccn.loc.gov/2008622210"], "campaigns": [], "contributor": ["united states. national park service"], "date": "2008", "dates": ["2008-01-01T00:00:00Z"], "description": ["\"*GPO: 2008--339-126/00819. Reprint 2008.\" Title from panel. Includes text, location map, and ill. (some col.). Text, 3 maps, and col. ill. on verso. Available also through the Library of Congress Web site as a raster image."], "digitized": true, "extract_timestamp": "2021-10-09T15:45:31.833Z", "group": ["gmd.mar", "catalog", "general-maps", "main-catalog"], "hassegments": false, "id": "http://www.loc.gov/item/2008622210/", "image_url": ["https://tile.loc.gov/storage-services/service/gmd/gmd408/g4082/g4082h/ct011881.gif", "https://tile.loc.gov/storage-services/service/gmd/gmd408/g4082/g4082h/ct011881.gif#h=150&w=79", "https://tile.loc.gov/image-services/iiif/service:gmd:gmd408:g4082:g4082h:ct011881/full/pct:12.5/0/default.jpg#h=1230&w=650", "https://tile.loc.gov/image-services/iiif/service:gmd:gmd408:g4082:g4082h:ct011881/full/pct:25/0/default.jpg#h=2460&w=1301"], "index": 7, "item": {"call_number": ["G4082.H7 2008 .U5"], "contributors": ["United States. National Park Service, cartographer."], "created_published": ["[Washington, D.C.] : National Park Service, [2008]"], "date": "2008", "digital_id": ["https://hdl.loc.gov/loc.gmd/g4082h.ct011881"], "format": ["cartographic"], "language": ["eng"], "location": ["Hopewell Culture National Historical Park (Ohio)"], "medium": ["1 map : col. ; 9 x 11 cm., on sheet 40 x 43 cm., folded to 10 x 21 cm."], "notes": ["\"*GPO: 2008--339-126/00819. Reprint 2008.\"", "Title from panel.", "Includes text, location map, and ill. (some col.).", "Text, 3 maps, and col. ill. on verso.", "Available also through the Library of Congress Web site as a raster image."], "number_former_id": ["https://www.loc.gov/item/2008622210", "https://www.loc.gov/item/15192597"], "other_title": ["Hopewell World"], "repository": ["Library of Congress Geography and Map Division Washington, D.C. 20540-4650 USA dcu"], "subjects": ["Hopewell Culture National Historical Park (Ohio)--Maps", "United States--Ohio--Hopewell Culture National Historical Park"], "title": "Hopewell Culture National Historical Park, Ohio"}, "language": ["english"], "location": ["united states", "ohio", "hopewell culture national historical park"], "location_country": ["united states"], "location_county": ["hopewell culture national historical park"], "location_state": ["ohio"], "mime_type": ["image/gif", "image/tiff", "image/jpeg", "image/jp2"], "number": ["http://www.loc.gov/item/2008622210", "2021-10-07t15:52:57", "http://www.loc.gov/item/15192597", "2008622210"], "number_former_id": ["http://www.loc.gov/item/2008622210", "http://www.loc.gov/item/15192597"], "number_lccn": ["2008622210"], "number_source_modified": ["2021-10-07t15:52:57"], "online_format": ["image"], "original_format": ["map"], "other_title": ["Hopewell World"], "partof": ["american memory", "general maps", "catalog", "geography and map division"], "resources": [{"files": 1, "image": "https://tile.loc.gov/storage-services/service/gmd/gmd408/g4082/g4082h/ct011881.gif", "url": "https://www.loc.gov/resource/g4082h.ct011881/"}], "shelf_id": "G4082.H7 2008 .U5", "site": ["ammem", "catalog"], "subject": ["united states", "maps", "hopewell culture national historical park", "hopewell culture national historical park (ohio)", "ohio"], "timestamp": "2021-10-09T15:46:23.267Z", "title": "Hopewell Culture National Historical Park, Ohio", "url": "https://www.loc.gov/item/2008622210/"}, {"access_restricted": false, "aka": ["https://hdl.loc.gov/loc.gmd/g4414a.ct011981", "http://www.loc.gov/resource/g4414a.ct011981/", "http://www.loc.gov/item/2019361212/", "http://lccn.loc.gov/2019361212"], "campaigns": [], "contributor": ["rosales, francisco", "garcia y solarer, cristobal"], "date": "1862", "dates": ["1862-01-01T00:00:00Z"], "description": ["Covering from Puebla (Ciudad de los Angeles) to Mexico City, passing through the Sierra Nevada Mountains and the Iztaccihuati and Popocatepeti volcanoes. Relief shown pictorially. Title from publisher's advertisement. Pen-and-ink and watercolors. Text on verso: El mapa que antecede esta fiel y legalmente copiado del original por el que suscribo segun su leal saber y entender; con interecion del Co. Franccisco Rosales paleografo e interprete del idioma mejicana del Archivo General de la Nacion en cuanto a la escritura, y voces del esperado idioma.  Mejico Abril 27 de 1862. Available also through the Library of Congress Web site as a raster image."], "digitized": true, "extract_timestamp": "2021-10-09T15:45:31.833Z", "group": ["gmd.mar", "catalog", "general-maps", "main-catalog"], "hassegments": false, "id": "http://www.loc.gov/item/2019361212/", "image_url": ["https://tile.loc.gov/storage-services/service/gmd/gmd4/g4414/g4414a/ct011981.gif", "https://tile.loc.gov/storage-services/service/gmd/gmd4/g4414/g4414a/ct011981.gif#h=300&w=500", "https://tile.loc.gov/image-services/iiif/service:gmd:gmd4:g4414:g4414a:ct011981/full/pct:12.5/0/default.jpg#h=479&w=799", "https://tile.loc.gov/image-services/iiif/service:gmd:gmd4:g4414:g4414a:ct011981/full/pct:25/0/default.jpg#h=959&w=1599"], "index": 8, "item": {"call_number": ["G4414.A512 1862 .R8"], "contributors": ["Garcia y Solarer, Cristobal, cartographer.", "Rosales, Francisco, active 1862, translator."], "created_published": ["Mexico, D.F. : Cristobal Garcia y Solarer, Francisco Rosales, 1862."], "date": "1862", "digital_id": ["https://hdl.loc.gov/loc.gmd/g4414a.ct011981"], "format": ["cartographic"], "genre": ["Manuscript maps"], "language": ["spa"], "location": ["Amecameca Region (Mexico)"], "medium": ["1 manuscript map : color ; 21 x 31 cm"], "notes": ["Covering from Puebla (Ciudad de los Angeles) to Mexico City, passing through the Sierra Nevada Mountains and the Iztaccihuati and Popocatepeti volcanoes.", "Relief shown pictorially.", "Title from publisher's advertisement.", "Pen-and-ink and watercolors.", "Text on verso: El mapa que antecede esta fiel y legalmente copiado del original por el que suscribo segun su leal saber y entender; con interecion del Co. Franccisco Rosales paleografo e interprete del idioma mejicana del Archivo General de la Nacion en cuanto a la escritura, y voces del esperado idioma.  Mejico Abril 27 de 1862.", "Available also through the Library of Congress Web site as a raster image."], "number_former_id": ["https://www.loc.gov/item/2019361212", "https://www.loc.gov/item/20499724"], "repository": ["Library of Congress Geography and Map Division Washington, D.C. 20540-4650 USA dcu"], "subjects": ["Amecameca Region (Mexico)--Maps", "Mexico--Amecameca Region"], "title": "[Ruta de los Volcanes - Amecameca and Environs]"}, "language": ["spanish"], "location": ["amecameca region", "mexico"], "location_country": ["mexico"], "location_county": ["amecameca region"], "mime_type": ["image/gif", "image/tiff", "image/jpeg", "image/jp2"], "number": ["2019361212", "http://www.loc.gov/item/20499724", "http://www.loc.gov/item/2019361212", "sheet", "2021-10-07t09:38:12"], "number_carrier_type": ["sheet"], "number_former_id": ["http://www.loc.gov/item/2019361212", "http://www.loc.gov/item/20499724"], "number_lccn": ["2019361212"], "number_source_modified": ["2021-10-07t09:38:12"], "online_format": ["image"], "original_format": ["map"], "other_title": [], "partof": ["american memory", "cities and towns", "catalog", "geography and map division"], "resources": [{"files": 1, "image": "https://tile.loc.gov/storage-services/service/gmd/gmd4/g4414/g4414a/ct011981.gif", "url": "https://www.loc.gov/resource/g4414a.ct011981/"}], "shelf_id": "G4414.A512 1862 .R8", "site": ["ammem", "catalog"], "subject": ["maps", "amecameca region (mexico)", "amecameca region", "manuscript maps", "mexico"], "timestamp": "2021-10-09T15:46:23.267Z", "title": "[Ruta de los Volcanes - Amecameca and Environs]", "url": "https://www.loc.gov/item/2019361212/"}]}