{"facets": [{"filters": [{"count": 16, "not": null, "off": null, "on": "https://www.loc.gov/search/?c=200&fo=json&sb=shelf-id&sq=group:gmd.mar+AND+number_source_modified:%5B2021-08-26+TO+2021-08-27%5D", "title": "true"}], "title": "Available Online", "type": "digitized"}, {"filters": [{"count": 16, "not": "https://www.loc.gov/search/?all=true&c=200&fa=original-format!:map&fo=json&sb=shelf-id&sq=group:gmd.mar+AND+number_source_modified:%5B2021-08-26+TO+2021-08-27%5D", "off": null, "on": "https://www.loc.gov/maps/?all=true&c=200&fo=json&sb=shelf-id&sq=group:gmd.mar+AND+number_source_modified:%5B2021-08-26+TO+2021-08-27%5D", "title": "map"}], "title": "Original Format", "type": "original-format"}, {"filters": [{"count": 16, "not": "https://www.loc.gov/search/?all=true&c=200&fa=online-format!:image&fo=json&sb=shelf-id&sq=group:gmd.mar+AND+number_source_modified:%5B2021-08-26+TO+2021-08-27%5D", "off": null, "on": "https://www.loc.gov/search/?all=true&c=200&fa=online-format:image&fo=json&sb=shelf-id&sq=group:gmd.mar+AND+number_source_modified:%5B2021-08-26+TO+2021-08-27%5D", "title": "image"}], "title": "Online Format", "type": "online-format"}, {"filters": [{"count": 4, "not": null, "off": null, "on": "https://www.loc.gov/search/?all=true&c=200&dates=1900/1999&fo=json&sb=shelf-id&sq=group:gmd.mar+AND+number_source_modified:%5B2021-08-26+TO+2021-08-27%5D", "term": "1900-01-01T00:00:00Z", "title": "1900 to 1999"}, {"count": 10, "not": null, "off": null, "on": "https://www.loc.gov/search/?all=true&c=200&dates=1800/1899&fo=json&sb=shelf-id&sq=group:gmd.mar+AND+number_source_modified:%5B2021-08-26+TO+2021-08-27%5D", "term": "1800-01-01T00:00:00Z", "title": "1800 to 1899"}, {"count": 2, "not": null, "off": null, "on": "https://www.loc.gov/search/?all=true&c=200&dates=1700/1799&fo=json&sb=shelf-id&sq=group:gmd.mar+AND+number_source_modified:%5B2021-08-26+TO+2021-08-27%5D", "term": "1700-01-01T00:00:00Z", "title": "1700 to 1799"}], "title": "Date", "type": "dates"}, {"filters": [{"count": 16, "not": "https://www.loc.gov/search/?all=true&c=200&fa=location!:united+states&fo=json&sb=shelf-id&sq=group:gmd.mar+AND+number_source_modified:%5B2021-08-26+TO+2021-08-27%5D", "off": null, "on": "https://www.loc.gov/search/?all=true&c=200&fa=location:united+states&fo=json&sb=shelf-id&sq=group:gmd.mar+AND+number_source_modified:%5B2021-08-26+TO+2021-08-27%5D", "title": "united states"}, {"count": 14, "not": "https://www.loc.gov/search/?all=true&c=200&fa=location!:district+of+columbia&fo=json&sb=shelf-id&sq=group:gmd.mar+AND+number_source_modified:%5B2021-08-26+TO+2021-08-27%5D", "off": null, "on": "https://www.loc.gov/search/?all=true&c=200&fa=location:district+of+columbia&fo=json&sb=shelf-id&sq=group:gmd.mar+AND+number_source_modified:%5B2021-08-26+TO+2021-08-27%5D", "title": "district of columbia"}, {"count": 14, "not": "https://www.loc.gov/search/?all=true&c=200&fa=location!:washington+d.c.&fo=json&sb=shelf-id&sq=group:gmd.mar+AND+number_source_modified:%5B2021-08-26+TO+2021-08-27%5D", "off": null, "on": "https://www.loc.gov/search/?all=true&c=200&fa=location:washington+d.c.&fo=json&sb=shelf-id&sq=group:gmd.mar+AND+number_source_modified:%5B2021-08-26+TO+2021-08-27%5D", "title": "washington d.c."}, {"count": 13, "not": "https://www.loc.gov/search/?all=true&c=200&fa=location!:washington&fo=json&sb=shelf-id&sq=group:gmd.mar+AND+number_source_modified:%5B2021-08-26+TO+2021-08-27%5D", "off": null, "on": "https://www.loc.gov/search/?all=true&c=200&fa=location:washington&fo=json&sb=shelf-id&sq=group:gmd.mar+AND+number_source_modified:%5B2021-08-26+TO+2021-08-27%5D", "title": "washington"}, {"count": 4, "not": "https://www.loc.gov/search/?all=true&c=200&fa=location!:georgetown&fo=json&sb=shelf-id&sq=group:gmd.mar+AND+number_source_modified:%5B2021-08-26+TO+2021-08-27%5D", "off": null, "on": "https://www.loc.gov/search/?all=true&c=200&fa=location:georgetown&fo=json&sb=shelf-id&sq=group:gmd.mar+AND+number_source_modified:%5B2021-08-26+TO+2021-08-27%5D", "title": "georgetown"}, {"count": 3, "not": "https://www.loc.gov/search/?all=true&c=200&fa=location!:maryland&fo=json&sb=shelf-id&sq=group:gmd.mar+AND+number_source_modified:%5B2021-08-26+TO+2021-08-27%5D", "off": null, "on": "https://www.loc.gov/search/?all=true&c=200&fa=location:maryland&fo=json&sb=shelf-id&sq=group:gmd.mar+AND+number_source_modified:%5B2021-08-26+TO+2021-08-27%5D", "title": "maryland"}, {"count": 2, "not": "https://www.loc.gov/search/?all=true&c=200&fa=location!:anacostia+river+valley&fo=json&sb=shelf-id&sq=group:gmd.mar+AND+number_source_modified:%5B2021-08-26+TO+2021-08-27%5D", "off": null, "on": "https://www.loc.gov/search/?all=true&c=200&fa=location:anacostia+river+valley&fo=json&sb=shelf-id&sq=group:gmd.mar+AND+number_source_modified:%5B2021-08-26+TO+2021-08-27%5D", "title": "anacostia river valley"}, {"count": 2, "not": "https://www.loc.gov/search/?all=true&c=200&fa=location!:anacostia+river+valley+%28washington%29&fo=json&sb=shelf-id&sq=group:gmd.mar+AND+number_source_modified:%5B2021-08-26+TO+2021-08-27%5D", "off": null, "on": "https://www.loc.gov/search/?all=true&c=200&fa=location:anacostia+river+valley+%28washington%29&fo=json&sb=shelf-id&sq=group:gmd.mar+AND+number_source_modified:%5B2021-08-26+TO+2021-08-27%5D", "title": "anacostia river valley (washington)"}, {"count": 2, "not": "https://www.loc.gov/search/?all=true&c=200&fa=location!:fifth+street&fo=json&sb=shelf-id&sq=group:gmd.mar+AND+number_source_modified:%5B2021-08-26+TO+2021-08-27%5D", "off": null, "on": "https://www.loc.gov/search/?all=true&c=200&fa=location:fifth+street&fo=json&sb=shelf-id&sq=group:gmd.mar+AND+number_source_modified:%5B2021-08-26+TO+2021-08-27%5D", "title": "fifth street"}, {"count": 2, "not": "https://www.loc.gov/search/?all=true&c=200&fa=location!:thirty&fo=json&sb=shelf-id&sq=group:gmd.mar+AND+number_source_modified:%5B2021-08-26+TO+2021-08-27%5D", "off": null, "on": "https://www.loc.gov/search/?all=true&c=200&fa=location:thirty&fo=json&sb=shelf-id&sq=group:gmd.mar+AND+number_source_modified:%5B2021-08-26+TO+2021-08-27%5D", "title": "thirty"}], "index": "https://www.loc.gov/search/index/location/?all=true&c=200&fo=json&sq=group:gmd.mar+AND+number_source_modified:%5B2021-08-26+TO+2021-08-27%5D", "title": "Location", "type": "location"}, {"filters": [{"count": 16, "not": "https://www.loc.gov/search/?all=true&c=200&fa=partof!:american+memory&fo=json&sb=shelf-id&sq=group:gmd.mar+AND+number_source_modified:%5B2021-08-26+TO+2021-08-27%5D", "off": null, "on": "https://www.loc.gov/search/?all=true&c=200&fa=partof:american+memory&fo=json&sb=shelf-id&sq=group:gmd.mar+AND+number_source_modified:%5B2021-08-26+TO+2021-08-27%5D", "title": "american memory"}, {"count": 16, "not": "https://www.loc.gov/search/?all=true&c=200&fa=partof!:catalog&fo=json&sb=shelf-id&sq=group:gmd.mar+AND+number_source_modified:%5B2021-08-26+TO+2021-08-27%5D", "off": null, "on": "https://www.loc.gov/search/?all=true&c=200&fa=partof:catalog&fo=json&sb=shelf-id&sq=group:gmd.mar+AND+number_source_modified:%5B2021-08-26+TO+2021-08-27%5D", "title": "catalog"}, {"count": 16, "not": "https://www.loc.gov/search/?all=true&c=200&fa=partof!:geography+and+map+division&fo=json&sb=shelf-id&sq=group:gmd.mar+AND+number_source_modified:%5B2021-08-26+TO+2021-08-27%5D", "off": null, "on": "https://www.loc.gov/search/?all=true&c=200&fa=partof:geography+and+map+division&fo=json&sb=shelf-id&sq=group:gmd.mar+AND+number_source_modified:%5B2021-08-26+TO+2021-08-27%5D", "title": "geography and map division"}, {"count": 13, "not": "https://www.loc.gov/search/?all=true&c=200&fa=partof!:cities+and+towns&fo=json&sb=shelf-id&sq=group:gmd.mar+AND+number_source_modified:%5B2021-08-26+TO+2021-08-27%5D", "off": null, "on": "https://www.loc.gov/search/?all=true&c=200&fa=partof:cities+and+towns&fo=json&sb=shelf-id&sq=group:gmd.mar+AND+number_source_modified:%5B2021-08-26+TO+2021-08-27%5D", "title": "cities and towns"}, {"count": 6, "not": "https://www.loc.gov/search/?all=true&c=200&fa=partof!:county+landownership+maps&fo=json&sb=shelf-id&sq=group:gmd.mar+AND+number_source_modified:%5B2021-08-26+TO+2021-08-27%5D", "off": null, "on": "https://www.loc.gov/search/?all=true&c=200&fa=partof:county+landownership+maps&fo=json&sb=shelf-id&sq=group:gmd.mar+AND+number_source_modified:%5B2021-08-26+TO+2021-08-27%5D", "title": "county landownership maps"}, {"count": 5, "not": "https://www.loc.gov/search/?all=true&c=200&fa=partof!:cultural+landscapes&fo=json&sb=shelf-id&sq=group:gmd.mar+AND+number_source_modified:%5B2021-08-26+TO+2021-08-27%5D", "off": null, "on": "https://www.loc.gov/search/?all=true&c=200&fa=partof:cultural+landscapes&fo=json&sb=shelf-id&sq=group:gmd.mar+AND+number_source_modified:%5B2021-08-26+TO+2021-08-27%5D", "title": "cultural landscapes"}, {"count": 3, "not": "https://www.loc.gov/search/?all=true&c=200&fa=partof!:general+maps&fo=json&sb=shelf-id&sq=group:gmd.mar+AND+number_source_modified:%5B2021-08-26+TO+2021-08-27%5D", "off": null, "on": "https://www.loc.gov/search/?all=true&c=200&fa=partof:general+maps&fo=json&sb=shelf-id&sq=group:gmd.mar+AND+number_source_modified:%5B2021-08-26+TO+2021-08-27%5D", "title": "general maps"}], "title": "Part of", "type": "partof"}, {"filters": [{"count": 14, "not": "https://www.loc.gov/search/?all=true&c=200&fa=contributor!:taggart,+hugh+t.+%28hugh+thomas%29&fo=json&sb=shelf-id&sq=group:gmd.mar+AND+number_source_modified:%5B2021-08-26+TO+2021-08-27%5D", "off": null, "on": "https://www.loc.gov/search/?all=true&c=200&fa=contributor:taggart,+hugh+t.+%28hugh+thomas%29&fo=json&sb=shelf-id&sq=group:gmd.mar+AND+number_source_modified:%5B2021-08-26+TO+2021-08-27%5D", "title": "taggart, hugh t. (hugh thomas)"}, {"count": 4, "not": "https://www.loc.gov/search/?all=true&c=200&fa=contributor!:carbery,+lewis&fo=json&sb=shelf-id&sq=group:gmd.mar+AND+number_source_modified:%5B2021-08-26+TO+2021-08-27%5D", "off": null, "on": "https://www.loc.gov/search/?all=true&c=200&fa=contributor:carbery,+lewis&fo=json&sb=shelf-id&sq=group:gmd.mar+AND+number_source_modified:%5B2021-08-26+TO+2021-08-27%5D", "title": "carbery, lewis"}, {"count": 3, "not": "https://www.loc.gov/search/?all=true&c=200&fa=contributor!:district+of+columbia.+office+of+the+surveyor&fo=json&sb=shelf-id&sq=group:gmd.mar+AND+number_source_modified:%5B2021-08-26+TO+2021-08-27%5D", "off": null, "on": "https://www.loc.gov/search/?all=true&c=200&fa=contributor:district+of+columbia.+office+of+the+surveyor&fo=json&sb=shelf-id&sq=group:gmd.mar+AND+number_source_modified:%5B2021-08-26+TO+2021-08-27%5D", "title": "district of columbia. office of the surveyor"}, {"count": 1, "not": "https://www.loc.gov/search/?all=true&c=200&fa=contributor!:bouscaren,+w.+s.&fo=json&sb=shelf-id&sq=group:gmd.mar+AND+number_source_modified:%5B2021-08-26+TO+2021-08-27%5D", "off": null, "on": "https://www.loc.gov/search/?all=true&c=200&fa=contributor:bouscaren,+w.+s.&fo=json&sb=shelf-id&sq=group:gmd.mar+AND+number_source_modified:%5B2021-08-26+TO+2021-08-27%5D", "title": "bouscaren, w. s."}, {"count": 1, "not": "https://www.loc.gov/search/?all=true&c=200&fa=contributor!:carpenter,+b.+d.+%28benjamin+d.%29&fo=json&sb=shelf-id&sq=group:gmd.mar+AND+number_source_modified:%5B2021-08-26+TO+2021-08-27%5D", "off": null, "on": "https://www.loc.gov/search/?all=true&c=200&fa=contributor:carpenter,+b.+d.+%28benjamin+d.%29&fo=json&sb=shelf-id&sq=group:gmd.mar+AND+number_source_modified:%5B2021-08-26+TO+2021-08-27%5D", "title": "carpenter, b. d. (benjamin d.)"}, {"count": 1, "not": "https://www.loc.gov/search/?all=true&c=200&fa=contributor!:district+of+columbia.+assessor%27s+office&fo=json&sb=shelf-id&sq=group:gmd.mar+AND+number_source_modified:%5B2021-08-26+TO+2021-08-27%5D", "off": null, "on": "https://www.loc.gov/search/?all=true&c=200&fa=contributor:district+of+columbia.+assessor%27s+office&fo=json&sb=shelf-id&sq=group:gmd.mar+AND+number_source_modified:%5B2021-08-26+TO+2021-08-27%5D", "title": "district of columbia. assessor's office"}, {"count": 1, "not": "https://www.loc.gov/search/?all=true&c=200&fa=contributor!:fenwick,+francis&fo=json&sb=shelf-id&sq=group:gmd.mar+AND+number_source_modified:%5B2021-08-26+TO+2021-08-27%5D", "off": null, "on": "https://www.loc.gov/search/?all=true&c=200&fa=contributor:fenwick,+francis&fo=json&sb=shelf-id&sq=group:gmd.mar+AND+number_source_modified:%5B2021-08-26+TO+2021-08-27%5D", "title": "fenwick, francis"}, {"count": 1, "not": "https://www.loc.gov/search/?all=true&c=200&fa=contributor!:mann,+arthur&fo=json&sb=shelf-id&sq=group:gmd.mar+AND+number_source_modified:%5B2021-08-26+TO+2021-08-27%5D", "off": null, "on": "https://www.loc.gov/search/?all=true&c=200&fa=contributor:mann,+arthur&fo=json&sb=shelf-id&sq=group:gmd.mar+AND+number_source_modified:%5B2021-08-26+TO+2021-08-27%5D", "title": "mann, arthur"}, {"count": 1, "not": "https://www.loc.gov/search/?all=true&c=200&fa=contributor!:starbuck,+c.+c.&fo=json&sb=shelf-id&sq=group:gmd.mar+AND+number_source_modified:%5B2021-08-26+TO+2021-08-27%5D", "off": null, "on": "https://www.loc.gov/search/?all=true&c=200&fa=contributor:starbuck,+c.+c.&fo=json&sb=shelf-id&sq=group:gmd.mar+AND+number_source_modified:%5B2021-08-26+TO+2021-08-27%5D", "title": "starbuck, c. c."}], "title": "Contributor", "type": "contributor"}, {"filters": [{"count": 16, "not": "https://www.loc.gov/search/?all=true&c=200&fa=subject!:united+states&fo=json&sb=shelf-id&sq=group:gmd.mar+AND+number_source_modified:%5B2021-08-26+TO+2021-08-27%5D", "off": null, "on": "https://www.loc.gov/search/?all=true&c=200&fa=subject:united+states&fo=json&sb=shelf-id&sq=group:gmd.mar+AND+number_source_modified:%5B2021-08-26+TO+2021-08-27%5D", "title": "united states"}, {"count": 14, "not": "https://www.loc.gov/search/?all=true&c=200&fa=subject!:district+of+columbia&fo=json&sb=shelf-id&sq=group:gmd.mar+AND+number_source_modified:%5B2021-08-26+TO+2021-08-27%5D", "off": null, "on": "https://www.loc.gov/search/?all=true&c=200&fa=subject:district+of+columbia&fo=json&sb=shelf-id&sq=group:gmd.mar+AND+number_source_modified:%5B2021-08-26+TO+2021-08-27%5D", "title": "district of columbia"}, {"count": 14, "not": "https://www.loc.gov/search/?all=true&c=200&fa=subject!:maps&fo=json&sb=shelf-id&sq=group:gmd.mar+AND+number_source_modified:%5B2021-08-26+TO+2021-08-27%5D", "off": null, "on": "https://www.loc.gov/search/?all=true&c=200&fa=subject:maps&fo=json&sb=shelf-id&sq=group:gmd.mar+AND+number_source_modified:%5B2021-08-26+TO+2021-08-27%5D", "title": "maps"}, {"count": 13, "not": "https://www.loc.gov/search/?all=true&c=200&fa=subject!:washington&fo=json&sb=shelf-id&sq=group:gmd.mar+AND+number_source_modified:%5B2021-08-26+TO+2021-08-27%5D", "off": null, "on": "https://www.loc.gov/search/?all=true&c=200&fa=subject:washington&fo=json&sb=shelf-id&sq=group:gmd.mar+AND+number_source_modified:%5B2021-08-26+TO+2021-08-27%5D", "title": "washington"}, {"count": 12, "not": "https://www.loc.gov/search/?all=true&c=200&fa=subject!:manuscript+maps&fo=json&sb=shelf-id&sq=group:gmd.mar+AND+number_source_modified:%5B2021-08-26+TO+2021-08-27%5D", "off": null, "on": "https://www.loc.gov/search/?all=true&c=200&fa=subject:manuscript+maps&fo=json&sb=shelf-id&sq=group:gmd.mar+AND+number_source_modified:%5B2021-08-26+TO+2021-08-27%5D", "title": "manuscript maps"}, {"count": 12, "not": "https://www.loc.gov/search/?all=true&c=200&fa=subject!:maps,+manuscript&fo=json&sb=shelf-id&sq=group:gmd.mar+AND+number_source_modified:%5B2021-08-26+TO+2021-08-27%5D", "off": null, "on": "https://www.loc.gov/search/?all=true&c=200&fa=subject:maps,+manuscript&fo=json&sb=shelf-id&sq=group:gmd.mar+AND+number_source_modified:%5B2021-08-26+TO+2021-08-27%5D", "title": "maps, manuscript"}, {"count": 12, "not": "https://www.loc.gov/search/?all=true&c=200&fa=subject!:washington+%28d.c.%29&fo=json&sb=shelf-id&sq=group:gmd.mar+AND+number_source_modified:%5B2021-08-26+TO+2021-08-27%5D", "off": null, "on": "https://www.loc.gov/search/?all=true&c=200&fa=subject:washington+%28d.c.%29&fo=json&sb=shelf-id&sq=group:gmd.mar+AND+number_source_modified:%5B2021-08-26+TO+2021-08-27%5D", "title": "washington (d.c.)"}, {"count": 7, "not": "https://www.loc.gov/search/?all=true&c=200&fa=subject!:real+property&fo=json&sb=shelf-id&sq=group:gmd.mar+AND+number_source_modified:%5B2021-08-26+TO+2021-08-27%5D", "off": null, "on": "https://www.loc.gov/search/?all=true&c=200&fa=subject:real+property&fo=json&sb=shelf-id&sq=group:gmd.mar+AND+number_source_modified:%5B2021-08-26+TO+2021-08-27%5D", "title": "real property"}, {"count": 6, "not": "https://www.loc.gov/search/?all=true&c=200&fa=subject!:streets&fo=json&sb=shelf-id&sq=group:gmd.mar+AND+number_source_modified:%5B2021-08-26+TO+2021-08-27%5D", "off": null, "on": "https://www.loc.gov/search/?all=true&c=200&fa=subject:streets&fo=json&sb=shelf-id&sq=group:gmd.mar+AND+number_source_modified:%5B2021-08-26+TO+2021-08-27%5D", "title": "streets"}, {"count": 5, "not": "https://www.loc.gov/search/?all=true&c=200&fa=subject!:charts,+diagrams,+etc&fo=json&sb=shelf-id&sq=group:gmd.mar+AND+number_source_modified:%5B2021-08-26+TO+2021-08-27%5D", "off": null, "on": "https://www.loc.gov/search/?all=true&c=200&fa=subject:charts,+diagrams,+etc&fo=json&sb=shelf-id&sq=group:gmd.mar+AND+number_source_modified:%5B2021-08-26+TO+2021-08-27%5D", "title": "charts, diagrams, etc"}], "index": "https://www.loc.gov/search/index/subject/?all=true&c=200&fo=json&sq=group:gmd.mar+AND+number_source_modified:%5B2021-08-26+TO+2021-08-27%5D", "title": "Subject", "type": "subject"}, {"filters": [{"count": 16, "not": "https://www.loc.gov/search/?all=true&c=200&fa=language!:english&fo=json&sb=shelf-id&sq=group:gmd.mar+AND+number_source_modified:%5B2021-08-26+TO+2021-08-27%5D", "off": null, "on": "https://www.loc.gov/search/?all=true&c=200&fa=language:english&fo=json&sb=shelf-id&sq=group:gmd.mar+AND+number_source_modified:%5B2021-08-26+TO+2021-08-27%5D", "title": "english"}, {"count": 1, "not": "https://www.loc.gov/search/?all=true&c=200&fa=language!:french&fo=json&sb=shelf-id&sq=group:gmd.mar+AND+number_source_modified:%5B2021-08-26+TO+2021-08-27%5D", "off": null, "on": "https://www.loc.gov/search/?all=true&c=200&fa=language:french&fo=json&sb=shelf-id&sq=group:gmd.mar+AND+number_source_modified:%5B2021-08-26+TO+2021-08-27%5D", "title": "french"}], "title": "Language", "type": "language"}, {"filters": [{"count": 16, "not": "https://www.loc.gov/search/?all=true&c=200&fa=access-restricted!:false&fo=json&sb=shelf-id&sq=group:gmd.mar+AND+number_source_modified:%5B2021-08-26+TO+2021-08-27%5D", "off": null, "on": "https://www.loc.gov/search/?all=true&c=200&fa=access-restricted:false&fo=json&sb=shelf-id&sq=group:gmd.mar+AND+number_source_modified:%5B2021-08-26+TO+2021-08-27%5D", "title": "false"}], "title": "Access Condition", "type": "access-restricted"}], "pagination": {"current": 1, "first": null, "from": 1, "last": null, "next": null, "of": 16, "page_list": [{"number": 1, "url": null}], "perpage": 200, "perpage_options": [25, 50, 100, 150], "previous": null, "results": "1 - 16", "to": 16, "total": 1}, "results": [{"access_restricted": false, "aka": ["http://www.loc.gov/item/78696099/", "http://hdl.loc.gov/loc.gmd/g3804n.ct005747", "http://www.loc.gov/resource/g3804n.ct005747/", "http://lccn.loc.gov/78696099"], "campaigns": [], "contributor": ["mann, arthur"], "date": "1920", "dates": ["1920-01-01T00:00:00Z"], "description": ["Scale 1:1,200; 1 in. = 100 ft. Manuscript; pen-and-ink and blue pencil. Guard sheet attached. Cadastral map. From the papers of Arthur William Mann in LC Manuscript Division. Available also through the Library of Congress Web site as a raster image. Vault AACR2: 700"], "digitized": true, "extract_timestamp": "2021-08-28T23:27:34.305Z", "group": ["gmd.mar", "catalog", "general-maps", "main-catalog"], "hassegments": false, "id": "http://www.loc.gov/item/78696099/", "image_url": ["https://tile.loc.gov/storage-services/service/gmd/gmd380/g3804/g3804n/ct005747.gif", "https://tile.loc.gov/storage-services/service/gmd/gmd380/g3804/g3804n/ct005747.gif#h=150&w=119", "https://tile.loc.gov/image-services/iiif/service:gmd:gmd380:g3804:g3804n:ct005747/full/pct:12.5/0/default.jpg#h=398&w=315", "https://tile.loc.gov/image-services/iiif/service:gmd:gmd380:g3804:g3804n:ct005747/full/pct:25/0/default.jpg#h=797&w=630"], "index": 1, "item": {"call_number": ["G3804.N4:2E2 192- .E2"], "contributors": ["Mann, Arthur, 1901-1963."], "created_published": ["[192-?]"], "date": "1920", "digital_id": ["http://hdl.loc.gov/loc.gmd/g3804n.ct005747"], "format": ["cartographic"], "genre": ["Cadastral maps", "Manuscript maps"], "language": ["eng"], "medium": ["1 map : col. ; on sheet 28 x 22 cm."], "notes": ["Scale 1:1,200; 1 in. = 100 ft.", "Manuscript; pen-and-ink and blue pencil.", "Guard sheet attached.", "Cadastral map.", "From the papers of Arthur William Mann in LC Manuscript Division.", "Available also through the Library of Congress Web site as a raster image.", "Vault", "AACR2: 700"], "number_former_id": ["https://www.loc.gov/item/78696099", "https://www.loc.gov/item/5444999"], "repository": ["Library of Congress Geography and Map Division Washington, D.C. 20540-4650 USA dcu"], "source_collection": ["Mann, Arthur, Arthur Mann map collection"], "subjects": ["Ebbets Field (New York, N.Y.)--Maps", "United States--New York (State)--New York--Ebbets Field"], "title": "Ebbets Field."}, "language": ["english"], "location": ["united states", "new york", "new york (state)"], "location_city": ["new york"], "location_country": ["united states"], "location_state": ["new york (state)"], "mime_type": ["image/gif", "image/tiff", "image/jpeg", "image/jp2"], "number": ["http://www.loc.gov/item/78696099", "78696099", "2021-08-26t12:47:53", "http://www.loc.gov/item/5444999"], "number_former_id": ["http://www.loc.gov/item/78696099", "http://www.loc.gov/item/5444999"], "number_lccn": ["78696099"], "number_source_modified": ["2021-08-26t12:47:53"], "online_format": ["image"], "original_format": ["map"], "other_title": [], "partof": ["american memory", "general maps", "catalog", "geography and map division"], "resources": [{"files": 1, "image": "https://tile.loc.gov/storage-services/service/gmd/gmd380/g3804/g3804n/ct005747.gif", "url": "https://www.loc.gov/resource/g3804n.ct005747/"}], "shelf_id": "G3804.N4:2E2 192- .E2", "site": ["ammem", "catalog"], "subject": ["cadastral maps", "ebbets field", "ebbets field (new york, n.y.)", "united states", "maps", "new york", "new york (state)", "manuscript maps"], "timestamp": "2021-08-28T23:29:05.645Z", "title": "Ebbets Field.", "url": "https://www.loc.gov/item/78696099/"}, {"access_restricted": false, "aka": ["http://www.loc.gov/item/87694288/", "http://hdl.loc.gov/loc.gmd/g3851b.ct004226", "http://www.loc.gov/resource/g3851b.ct004226/", "http://lccn.loc.gov/87694288"], "campaigns": [], "contributor": ["taggart, hugh t. (hugh thomas)"], "date": "1800", "dates": ["1800-01-01T00:00:00Z"], "description": ["From the Taggart Estate papers. Manuscript--ink and pencil. Lacks corner section and mounted on cloth backing. Includes unidentified depth profile--possibly of Anacostia River. Available also through the Library of Congress Web site as a raster image. Vault DCP"], "digitized": true, "extract_timestamp": "2021-08-28T23:27:34.305Z", "group": ["gmd.mar", "catalog", "general-maps", "main-catalog"], "hassegments": false, "id": "http://www.loc.gov/item/87694288/", "image_url": ["https://tile.loc.gov/storage-services/service/gmd/gmd385/g3851/g3851b/ct004226.gif", "https://tile.loc.gov/storage-services/service/gmd/gmd385/g3851/g3851b/ct004226.gif#h=113&w=150", "https://tile.loc.gov/image-services/iiif/service:gmd:gmd385:g3851:g3851b:ct004226/full/pct:12.5/0/default.jpg#h=640&w=847", "https://tile.loc.gov/image-services/iiif/service:gmd:gmd385:g3851:g3851b:ct004226/full/pct:25/0/default.jpg#h=1281&w=1694"], "index": 2, "item": {"call_number": ["G3851.B3 18-- .S8"], "contributors": ["Taggart, Hugh T. (Hugh Thomas), 1844-1914."], "created_published": ["[18--?]"], "date": "1800", "digital_id": ["http://hdl.loc.gov/loc.gmd/g3851b.ct004226"], "format": ["cartographic"], "language": ["eng"], "location": ["Washington (D.C.)"], "medium": ["1 map : ms. ; 17 x 50 cm., on sheet 43 x 58 cm."], "notes": ["From the Taggart Estate papers.", "Manuscript--ink and pencil.", "Lacks corner section and mounted on cloth backing.", "Includes unidentified depth profile--possibly of Anacostia River.", "Available also through the Library of Congress Web site as a raster image.", "Vault", "DCP"], "number_former_id": ["https://www.loc.gov/item/87694288", "https://www.loc.gov/item/5498024"], "repository": ["Library of Congress Geography and Map Division Washington, D.C. 20540-4650 USA dcu"], "source_collection": ["Taggart, Hugh T. (Hugh Thomas), Taggart Estate map collection"], "subjects": ["Washington (D.C.)--Surveys--Maps", "Washington (D.C.)--Maps, Manuscript", "Manuscript maps", "United States--District of Columbia--Washington"], "title": "[Survey of an unidentified area in Washington D.C.]."}, "language": ["english"], "location": ["united states", "washington d.c.", "district of columbia", "washington"], "location_city": ["washington"], "location_country": ["united states"], "location_state": ["district of columbia"], "mime_type": ["image/gif", "image/tiff", "image/jpeg", "image/jp2"], "number": ["2021-08-26t15:28:07", "http://www.loc.gov/item/5498024", "http://www.loc.gov/item/87694288", "87694288"], "number_former_id": ["http://www.loc.gov/item/87694288", "http://www.loc.gov/item/5498024"], "number_lccn": ["87694288"], "number_source_modified": ["2021-08-26t15:28:07"], "online_format": ["image"], "original_format": ["map"], "other_title": [], "partof": ["american memory", "cities and towns", "catalog", "geography and map division"], "resources": [{"files": 1, "image": "https://tile.loc.gov/storage-services/service/gmd/gmd385/g3851/g3851b/ct004226.gif", "url": "https://www.loc.gov/resource/g3851b.ct004226/"}], "shelf_id": "G3851.B3 18-- .S8", "site": ["ammem", "catalog"], "subject": ["washington (d.c.)", "surveys", "maps, manuscript", "washington", "united states", "maps", "district of columbia", "manuscript maps"], "timestamp": "2021-08-28T23:29:05.645Z", "title": "[Survey of an unidentified area in Washington D.C.].", "url": "https://www.loc.gov/item/87694288/"}, {"access_restricted": false, "aka": ["http://www.loc.gov/resource/g3852a.la002223/", "http://www.loc.gov/item/88690689/", "http://hdl.loc.gov/loc.gmd/g3852a.la002223", "http://lccn.loc.gov/88690689"], "campaigns": [], "contributor": ["taggart, hugh t. (hugh thomas)"], "date": "1900", "dates": ["1900-01-01T00:00:00Z"], "description": ["Property tracts shown in red. Also shows block numbers, tide lines, and 5-ft. contour. India ink, red ink, and col. pencil. Oriented with north toward the upper right. Fold-lined and halved. Available also through the Library of Congress Web site as a raster image. Vault DCP"], "digitized": true, "extract_timestamp": "2021-08-28T23:27:34.305Z", "group": ["gmd.mar", "catalog", "general-maps", "main-catalog"], "hassegments": false, "id": "http://www.loc.gov/item/88690689/", "image_url": ["https://tile.loc.gov/storage-services/service/gmd/gmd385/g3852/g3852a/la002223.gif", "https://tile.loc.gov/storage-services/service/gmd/gmd385/g3852/g3852a/la002223.gif#h=67&w=150", "https://tile.loc.gov/image-services/iiif/service:gmd:gmd385:g3852:g3852a:la002223/full/pct:12.5/0/default.jpg#h=1377&w=3101", "https://tile.loc.gov/image-services/iiif/service:gmd:gmd385:g3852:g3852a:la002223/full/pct:25/0/default.jpg#h=2754&w=6202"], "index": 3, "item": {"call_number": ["G3852.A5G46 190- .M3"], "contributors": ["Taggart, Hugh T. (Hugh Thomas), 1844-1914."], "created_published": ["[190-?]"], "date": "1900", "digital_id": ["http://hdl.loc.gov/loc.gmd/g3852a.la002223"], "format": ["cartographic"], "language": ["eng"], "location": ["Anacostia River Valley (Md. and Washington, D.C.)"], "medium": ["1 map : col., ms., tracing linen ; 62 x 185 cm., on sheet 96 x 212 cm."], "notes": ["Property tracts shown in red. Also shows block numbers, tide lines, and 5-ft. contour.", "India ink, red ink, and col. pencil.", "Oriented with north toward the upper right.", "Fold-lined and halved.", "Available also through the Library of Congress Web site as a raster image.", "Vault", "DCP"], "number_former_id": ["https://www.loc.gov/item/88690689", "https://www.loc.gov/item/5499940"], "repository": ["Library of Congress Geography and Map Division Washington, D.C. 20540-4650 USA dcu"], "source_collection": ["Taggart, Hugh T. (Hugh Thomas), Taggart Estate map collection"], "subjects": ["Real property--Anacostia River Valley (Md. and Washington, D.C.)--Maps", "Anacostia River Valley (Md. and Washington, D.C.)--Maps, Manuscript", "Manuscript maps", "United States--District of Columbia--Washington", "United States--District of Columbia--Anacostia River Valley (Washington)", "United States--Maryland--Anacostia River Valley"], "title": "[Map of landholdings along the Anacostia River in Washington, D.C.]."}, "language": ["english"], "location": ["washington d.c.", "anacostia river valley (washington)", "washington", "united states", "district of columbia", "maryland", "anacostia river valley"], "location_city": ["washington"], "location_country": ["united states"], "location_county": ["anacostia river valley (washington)", "anacostia river valley"], "location_state": ["district of columbia", "maryland"], "mime_type": ["image/gif", "image/tiff", "image/jpeg", "image/jp2"], "number": ["2021-08-26t15:27:43", "http://www.loc.gov/item/5499940", "88690689", "http://www.loc.gov/item/88690689"], "number_former_id": ["http://www.loc.gov/item/88690689", "http://www.loc.gov/item/5499940"], "number_lccn": ["88690689"], "number_source_modified": ["2021-08-26t15:27:43"], "online_format": ["image"], "original_format": ["map"], "other_title": [], "partof": ["american memory", "catalog", "county landownership maps", "geography and map division", "cultural landscapes"], "resources": [{"files": 1, "image": "https://tile.loc.gov/storage-services/service/gmd/gmd385/g3852/g3852a/la002223.gif", "url": "https://www.loc.gov/resource/g3852a.la002223/"}], "shelf_id": "G3852.A5G46 190- .M3", "site": ["ammem", "catalog"], "subject": ["maps, manuscript", "anacostia river valley (washington)", "washington", "united states", "maps", "district of columbia", "anacostia river valley (md. and washington, d.c.)", "real property", "anacostia river valley", "maryland", "manuscript maps"], "timestamp": "2021-08-28T23:29:05.645Z", "title": "[Map of landholdings along the Anacostia River in Washington, D.C.].", "url": "https://www.loc.gov/item/88690689/"}, {"access_restricted": false, "aka": ["http://hdl.loc.gov/loc.gmd/g3852a.la002224", "http://www.loc.gov/item/88690690/", "http://www.loc.gov/resource/g3852a.la002224/", "http://lccn.loc.gov/88690690"], "campaigns": [], "contributor": ["taggart, hugh t. (hugh thomas)", "district of columbia. assessor's office"], "date": "1909", "dates": ["1909-01-01T00:00:00Z"], "description": ["Also shows original land tracts and tract numbers. India ink, col. inks, blue pencil, and lead pencil. Oriented with north toward the upper right. Fold-lined. Available also through the Library of Congress Web site as a raster image. Vault DCP"], "digitized": true, "extract_timestamp": "2021-08-28T23:27:34.305Z", "group": ["gmd.mar", "catalog", "general-maps", "main-catalog"], "hassegments": false, "id": "http://www.loc.gov/item/88690690/", "image_url": ["https://tile.loc.gov/storage-services/service/gmd/gmd385/g3852/g3852a/la002224.gif", "https://tile.loc.gov/storage-services/service/gmd/gmd385/g3852/g3852a/la002224.gif#h=47&w=150", "https://tile.loc.gov/image-services/iiif/service:gmd:gmd385:g3852:g3852a:la002224/full/pct:12.5/0/default.jpg#h=1050&w=3340", "https://tile.loc.gov/image-services/iiif/service:gmd:gmd385:g3852:g3852a:la002224/full/pct:25/0/default.jpg#h=2101&w=6681"], "index": 4, "item": {"call_number": ["G3852.A5G46 1909 .D5"], "contributors": ["District of Columbia. Assessor's Office.", "Taggart, Hugh T. (Hugh Thomas), 1844-1914."], "created_published": ["[1909]"], "date": "1909", "digital_id": ["http://hdl.loc.gov/loc.gmd/g3852a.la002224"], "format": ["cartographic"], "language": ["eng"], "location": ["Anacostia River Valley (Md. and Washington, D.C.)"], "medium": ["1 map : col., ms., tracing linen ; 73 x 229 cm."], "notes": ["Also shows original land tracts and tract numbers.", "India ink, col. inks, blue pencil, and lead pencil.", "Oriented with north toward the upper right.", "Fold-lined.", "Available also through the Library of Congress Web site as a raster image.", "Vault", "DCP"], "number_former_id": ["https://www.loc.gov/item/88690690", "https://www.loc.gov/item/5499941"], "repository": ["Library of Congress Geography and Map Division Washington, D.C. 20540-4650 USA dcu"], "source_collection": ["Taggart, Hugh T. (Hugh Thomas), Taggart Estate map collection"], "subjects": ["Real property--Anacostia River Valley (Md. and Washington, D.C.)--Maps", "Land grants--Anacostia River Valley (Md. and Washington, D.C.)--Maps", "Anacostia River Valley (Md. and Washington, D.C.)--Maps, Manuscript", "Manuscript maps", "United States--District of Columbia--Anacostia River Valley (Washington)", "United States--Maryland--Anacostia River Valley"], "title": "Map showing holdings along Eastern Branch"}, "language": ["english"], "location": ["washington d.c.", "anacostia river valley (washington)", "united states", "district of columbia", "maryland", "anacostia river valley"], "location_country": ["united states"], "location_county": ["anacostia river valley (washington)", "anacostia river valley"], "location_state": ["district of columbia", "maryland"], "mime_type": ["image/gif", "image/tiff", "image/jpeg", "image/jp2"], "number": ["88690690", "http://www.loc.gov/item/88690690", "2021-08-26t14:31:14", "http://www.loc.gov/item/5499941"], "number_former_id": ["http://www.loc.gov/item/88690690", "http://www.loc.gov/item/5499941"], "number_lccn": ["88690690"], "number_source_modified": ["2021-08-26t14:31:14"], "online_format": ["image"], "original_format": ["map"], "other_title": [], "partof": ["american memory", "cities and towns", "catalog", "county landownership maps", "geography and map division"], "resources": [{"files": 1, "image": "https://tile.loc.gov/storage-services/service/gmd/gmd385/g3852/g3852a/la002224.gif", "url": "https://www.loc.gov/resource/g3852a.la002224/"}], "shelf_id": "G3852.A5G46 1909 .D5", "site": ["ammem", "catalog"], "subject": ["maps, manuscript", "anacostia river valley (washington)", "land grants", "united states", "maps", "district of columbia", "anacostia river valley (md. and washington, d.c.)", "real property", "anacostia river valley", "maryland", "manuscript maps"], "timestamp": "2021-08-28T23:29:05.645Z", "title": "Map showing holdings along Eastern Branch", "url": "https://www.loc.gov/item/88690690/"}, {"access_restricted": false, "aka": ["http://www.loc.gov/resource/g3852d.ct004300/", "http://www.loc.gov/item/88693340/", "http://hdl.loc.gov/loc.gmd/g3852d.ct004300", "http://lccn.loc.gov/88693340"], "campaigns": [], "contributor": ["carbery, lewis", "taggart, hugh t. (hugh thomas)"], "date": "1858", "dates": ["1858-01-01T00:00:00Z"], "description": ["Covers Dent Place between 33rd and 34th streets N.W., Georgetown, Washington D.C. Pen-and-ink with lead-pencil guidelines. Soiled and stained. Includes note and outline map of street. On verso in ink: Profile of 6th Street between Frederick & Market streets, 1858, Geotown D.C. No. 109, page 4. Available also through the Library of Congress Web site as a raster image. Phillips. Washington 505 Vault DCP"], "digitized": true, "extract_timestamp": "2021-08-28T23:27:34.305Z", "group": ["gmd.mar", "catalog", "general-maps", "main-catalog"], "hassegments": false, "id": "http://www.loc.gov/item/88693340/", "image_url": ["https://tile.loc.gov/storage-services/service/gmd/gmd385/g3852/g3852d/ct004300.gif", "https://tile.loc.gov/storage-services/service/gmd/gmd385/g3852/g3852d/ct004300.gif#h=150&w=116", "https://tile.loc.gov/image-services/iiif/service:gmd:gmd385:g3852:g3852d:ct004300/full/pct:12.5/0/default.jpg#h=603&w=466", "https://tile.loc.gov/image-services/iiif/service:gmd:gmd385:g3852:g3852d:ct004300/full/pct:25/0/default.jpg#h=1207&w=932"], "index": 5, "item": {"call_number": ["G3852.D55N23 1858 .C3"], "contributors": ["Carbery, Lewis.", "Taggart, Hugh T. (Hugh Thomas), 1844-1914."], "created_published": ["1858."], "date": "1858", "digital_id": ["http://hdl.loc.gov/loc.gmd/g3852d.ct004300"], "format": ["cartographic"], "language": ["eng"], "location": ["Washington (D.C.)", "Dent Place (Washington, D.C.)"], "medium": ["1 profile : ms. ; 28 x 22 cm., on sheet 42 x 33 cm."], "notes": ["Covers Dent Place between 33rd and 34th streets N.W., Georgetown, Washington D.C.", "Pen-and-ink with lead-pencil guidelines.", "Soiled and stained.", "Includes note and outline map of street.", "On verso in ink: Profile of 6th Street between Frederick & Market streets, 1858, Geotown D.C. No. 109, page 4.", "Available also through the Library of Congress Web site as a raster image.", "Phillips. Washington 505", "Vault", "DCP"], "number_former_id": ["https://www.loc.gov/item/88693340", "https://www.loc.gov/item/5502284"], "repository": ["Library of Congress Geography and Map Division Washington, D.C. 20540-4650 USA dcu"], "source_collection": ["Taggart, Hugh T. (Hugh Thomas), Taggart Estate map collection"], "subjects": ["Dent Place (Washington, D.C.)--Maps, Manuscript", "Streets--Washington (D.C.)--Charts, diagrams, etc", "Manuscript maps", "United States--District of Columbia--Washington--Dent Place"], "title": "Profile of 6th Street between Frederick and Market streets"}, "language": ["english"], "location": ["united states", "washington d.c.", "dent place", "district of columbia", "washington"], "location_city": ["washington"], "location_country": ["united states"], "location_state": ["district of columbia"], "mime_type": ["image/gif", "image/tiff", "image/jpeg", "image/jp2"], "number": ["88693340", "2021-08-26t14:18:21", "http://www.loc.gov/item/5502284", "http://www.loc.gov/item/88693340"], "number_former_id": ["http://www.loc.gov/item/88693340", "http://www.loc.gov/item/5502284"], "number_lccn": ["88693340"], "number_source_modified": ["2021-08-26t14:18:21"], "online_format": ["image"], "original_format": ["map"], "other_title": [], "partof": ["american memory", "cities and towns", "catalog", "geography and map division"], "resources": [{"files": 1, "image": "https://tile.loc.gov/storage-services/service/gmd/gmd385/g3852/g3852d/ct004300.gif", "url": "https://www.loc.gov/resource/g3852d.ct004300/"}], "shelf_id": "G3852.D55N23 1858 .C3", "site": ["ammem", "catalog"], "subject": ["maps, manuscript", "dent place", "washington (d.c.)", "washington", "streets", "charts, diagrams, etc", "dent place (washington, d.c.)", "united states", "district of columbia", "manuscript maps"], "timestamp": "2021-08-28T23:29:05.645Z", "title": "Profile of 6th Street between Frederick and Market streets", "url": "https://www.loc.gov/item/88693340/"}, {"access_restricted": false, "aka": ["http://www.loc.gov/item/88690829/", "http://hdl.loc.gov/loc.gmd/g3852f.ct004920", "http://www.loc.gov/resource/g3852f.ct004920/", "http://lccn.loc.gov/88690829"], "campaigns": [], "contributor": ["taggart, hugh t. (hugh thomas)", "starbuck, c. c."], "date": "1860", "dates": ["1860-01-01T00:00:00Z"], "description": ["Shows foundry buildings and \"Depot for guns.\" Also covers part of Potomac River waterfront and Chesapeake and Ohio Canal. Relief shown by hachures. Accompanied by ill.: Plan & elevations of Foundry. 1 sheet ; 54 x 66 cm. LC copy soiled and fold-lined. Available also through the Library of Congress Web site as a raster image. DCP"], "digitized": true, "extract_timestamp": "2021-08-28T23:27:34.305Z", "group": ["gmd.mar", "catalog", "general-maps", "main-catalog"], "hassegments": false, "id": "http://www.loc.gov/item/88690829/", "image_url": ["https://tile.loc.gov/storage-services/service/gmd/gmd385/g3852/g3852f/ct004920.gif", "https://tile.loc.gov/storage-services/service/gmd/gmd385/g3852/g3852f/ct004920.gif#h=63&w=150", "https://tile.loc.gov/image-services/iiif/service:gmd:gmd385:g3852:g3852f:ct004920/full/pct:12.5/0/default.jpg#h=847&w=2004", "https://tile.loc.gov/image-services/iiif/service:gmd:gmd385:g3852:g3852f:ct004920/full/pct:25/0/default.jpg#h=1694&w=4008"], "index": 6, "item": {"call_number": ["G3852.F68 186- .S7"], "contributors": ["Starbuck, C. C.", "Taggart, Hugh T. (Hugh Thomas), 1844-1914."], "created_published": ["[Washington? : s.n., 186-?]"], "date": "1860", "digital_id": ["http://hdl.loc.gov/loc.gmd/g3852f.ct004920"], "format": ["cartographic"], "language": ["eng"], "location": ["Washington (D.C.)", "Foundry (Washington, D.C.)", "Chesapeake and Ohio Canal (Md. and Washington, D.C.)"], "medium": ["1 map : cloth backing ; 54 x 66 cm."], "notes": ["Shows foundry buildings and \"Depot for guns.\"", "Also covers part of Potomac River waterfront and Chesapeake and Ohio Canal.", "Relief shown by hachures.", "Accompanied by ill.: Plan & elevations of Foundry. 1 sheet ; 54 x 66 cm.", "LC copy soiled and fold-lined.", "Available also through the Library of Congress Web site as a raster image.", "DCP"], "number_former_id": ["https://www.loc.gov/item/88690829", "https://www.loc.gov/item/5500080"], "repository": ["Library of Congress Geography and Map Division Washington, D.C. 20540-4650 USA dcu"], "source_collection": ["Taggart, Hugh T. (Hugh Thomas), Taggart Estate map collection"], "subjects": ["Foundry (Washington, D.C.)--Maps", "Foundry (Washington, D.C.)--Aerial views", "Waterfronts--Washington (D.C.)--Maps", "Chesapeake and Ohio Canal (Md. and Washington, D.C.)--Maps", "United States--District of Columbia--Washington--Foundry", "United States--District of Columbia--Washington", "United States--District of Columbia--Chesapeake and Ohio Canal"], "title": "Plan of Foundry site : [Washington D.C.]"}, "language": ["english"], "location": ["washington d.c.", "washington", "chesapeake", "chesapeake and ohio canal", "foundry", "united states", "district of columbia", "maryland", "ohio canal"], "location_city": ["washington", "chesapeake and ohio canal"], "location_country": ["united states"], "location_state": ["district of columbia"], "mime_type": ["image/gif", "image/tiff", "image/jpeg", "image/jp2"], "number": ["88690829", "http://www.loc.gov/item/88690829", "http://www.loc.gov/item/5500080", "2021-08-26t14:43:29"], "number_former_id": ["http://www.loc.gov/item/88690829", "http://www.loc.gov/item/5500080"], "number_lccn": ["88690829"], "number_source_modified": ["2021-08-26t14:43:29"], "online_format": ["image"], "original_format": ["map"], "other_title": [], "partof": ["american memory", "cities and towns", "catalog", "geography and map division"], "resources": [{"files": 1, "image": "https://tile.loc.gov/storage-services/service/gmd/gmd385/g3852/g3852f/ct004920.gif", "url": "https://www.loc.gov/resource/g3852f.ct004920/"}], "shelf_id": "G3852.F68 186- .S7", "site": ["ammem", "catalog"], "subject": ["washington (d.c.)", "chesapeake and ohio canal (md. and washington, d.c.)", "aerial views", "foundry", "washington", "waterfronts", "united states", "maps", "district of columbia", "foundry (washington, d.c.)", "chesapeake and ohio canal"], "timestamp": "2021-08-28T23:29:05.645Z", "title": "Plan of Foundry site : [Washington D.C.]", "url": "https://www.loc.gov/item/88690829/"}, {"access_restricted": false, "aka": ["http://www.loc.gov/item/88693336/", "http://hdl.loc.gov/loc.gmd/g3852f.la002259", "http://www.loc.gov/resource/g3852f.la002259/", "http://lccn.loc.gov/88693336"], "campaigns": [], "contributor": ["taggart, hugh t. (hugh thomas)"], "date": "1800", "dates": ["1800-01-01T00:00:00Z"], "description": ["Cadastral survey maps. Title in ink on verso. \"Done for Mr. William Redin.\" At upper left in large letters: W. Redin Esq. Brown and black inks with additions in lead pencil. Soiled and cracked along edges. On verso in ink: Index no. 58, page 2. No. 58. Available also through the Library of Congress Web site as a raster image. Phillips. Washington 501 Vault DCP"], "digitized": true, "extract_timestamp": "2021-08-28T23:27:34.305Z", "group": ["gmd.mar", "catalog", "general-maps", "main-catalog"], "hassegments": false, "id": "http://www.loc.gov/item/88693336/", "image_url": ["https://tile.loc.gov/storage-services/service/gmd/gmd385/g3852/g3852f/la002259.gif", "https://tile.loc.gov/storage-services/service/gmd/gmd385/g3852/g3852f/la002259.gif#h=118&w=150", "https://tile.loc.gov/image-services/iiif/service:gmd:gmd385:g3852:g3852f:la002259/full/pct:12.5/0/default.jpg#h=658&w=835", "https://tile.loc.gov/image-services/iiif/service:gmd:gmd385:g3852:g3852f:la002259/full/pct:25/0/default.jpg#h=1317&w=1670"], "index": 7, "item": {"call_number": ["G3852.F8G46 18-- .F7"], "contents": ["[Frogland] -- [H. Ball's lot]."], "contributors": ["Taggart, Hugh T. (Hugh Thomas), 1844-1914."], "created_published": ["[18--]"], "date": "1800", "digital_id": ["http://hdl.loc.gov/loc.gmd/g3852f.la002259"], "format": ["cartographic"], "language": ["eng"], "location": ["Washington (D.C.)", "Virginia", "Frogland (Washington, D.C.)"], "medium": ["2 maps on 1 sheet : ms. ; 27 x 22 cm. and 25 x 22 cm., sheet 45 x 57 cm."], "notes": ["Cadastral survey maps.", "Title in ink on verso.", "\"Done for Mr. William Redin.\"", "At upper left in large letters: W. Redin Esq.", "Brown and black inks with additions in lead pencil.", "Soiled and cracked along edges.", "On verso in ink: Index no. 58, page 2. No. 58.", "Available also through the Library of Congress Web site as a raster image.", "Phillips. Washington 501", "Vault", "DCP"], "number_former_id": ["https://www.loc.gov/item/88693336", "https://www.loc.gov/item/5502280"], "repository": ["Library of Congress Geography and Map Division Washington, D.C. 20540-4650 USA dcu"], "source_collection": ["Taggart, Hugh T. (Hugh Thomas), Taggart Estate map collection"], "subjects": ["Frogland (Washington, D.C.)--Maps, Manuscript", "Real property--Washington (D.C.)--Surveys--Maps", "Real property--Virginia--Surveys--Maps", "Redin, William--Homes and haunts--Washington (D.C.)--Maps", "Ball, H.--Homes and haunts--Virginia--Maps", "Manuscript maps", "United States--District of Columbia--Washington--Frogland", "United States--District of Columbia--Washington", "United States--Virginia"], "title": "Frogland, Georgetown D.C. & H. Balls lot, Viginia [sic]."}, "language": ["english"], "location": ["washington d.c.", "washington", "virginia", "frogland", "united states", "district of columbia"], "location_city": ["washington"], "location_country": ["united states"], "location_state": ["district of columbia", "virginia"], "mime_type": ["image/gif", "image/tiff", "image/jpeg", "image/jp2"], "number": ["http://www.loc.gov/item/88693336", "2021-08-26t13:38:00", "88693336", "http://www.loc.gov/item/5502280"], "number_former_id": ["http://www.loc.gov/item/88693336", "http://www.loc.gov/item/5502280"], "number_lccn": ["88693336"], "number_source_modified": ["2021-08-26t13:38:00"], "online_format": ["image"], "original_format": ["map"], "other_title": [], "partof": ["county landownership maps", "cultural landscapes", "cities and towns", "catalog", "american memory", "geography and map division"], "resources": [{"files": 1, "image": "https://tile.loc.gov/storage-services/service/gmd/gmd385/g3852/g3852f/la002259.gif", "url": "https://www.loc.gov/resource/g3852f.la002259/"}], "shelf_id": "G3852.F8G46 18-- .F7", "site": ["ammem", "catalog"], "subject": ["frogland (washington, d.c.)", "maps, manuscript", "surveys", "washington (d.c.)", "redin, william", "washington", "virginia", "frogland", "united states", "maps", "homes and haunts", "district of columbia", "real property", "ball, h.", "manuscript maps"], "timestamp": "2021-08-28T23:29:05.645Z", "title": "Frogland, Georgetown D.C. & H. Balls lot, Viginia [sic].", "url": "https://www.loc.gov/item/88693336/"}, {"access_restricted": false, "aka": ["http://www.loc.gov/item/88693289/", "http://www.loc.gov/resource/g3852g.la002257/", "http://hdl.loc.gov/loc.gmd/g3852g.la002257", "http://lccn.loc.gov/88693289"], "campaigns": [], "contributor": ["district of columbia. office of the surveyor", "taggart, hugh t. (hugh thomas)", "fenwick, francis"], "date": "1814", "dates": ["1814-01-01T00:00:00Z"], "description": ["Cadastral map showing block numbers. \"A present from Francis Fenwick to the Honorable the Corporation of George-town.\" In upper left corner: Hugh T. Taggart's. India ink. Brittle, missing small sections, halved, and mounted on cloth backing. Includes 3 insets and index to points of interest. Available also through the Library of Congress Web site as a raster image. Phillips. Washington 512 Vault DCP"], "digitized": true, "extract_timestamp": "2021-08-28T23:27:34.305Z", "group": ["gmd.mar", "catalog", "general-maps", "main-catalog"], "hassegments": false, "id": "http://www.loc.gov/item/88693289/", "image_url": ["https://tile.loc.gov/storage-services/service/gmd/gmd385/g3852/g3852g/la002257.gif", "https://tile.loc.gov/storage-services/service/gmd/gmd385/g3852/g3852g/la002257.gif#h=108&w=150", "https://tile.loc.gov/image-services/iiif/service:gmd:gmd385:g3852:g3852g:la002257/full/pct:12.5/0/default.jpg#h=1155&w=1601", "https://tile.loc.gov/image-services/iiif/service:gmd:gmd385:g3852:g3852g:la002257/full/pct:25/0/default.jpg#h=2310&w=3202"], "index": 8, "item": {"call_number": ["G3852.G43G46 1814 .F4"], "contributors": ["Fenwick, Francis.", "Taggart, Hugh T. (Hugh Thomas), 1844-1914.", "District of Columbia. Office of the Surveyor."], "created_published": ["[1814?]"], "date": "1814", "digital_id": ["http://hdl.loc.gov/loc.gmd/g3852g.la002257"], "format": ["cartographic"], "language": ["eng"], "location": ["Washington (D.C.)", "Georgetown (Washington, D.C.)"], "medium": ["1 map : ms., tracing linen ; 72 x 104 cm."], "notes": ["Cadastral map showing block numbers.", "\"A present from Francis Fenwick to the Honorable the Corporation of George-town.\"", "In upper left corner: Hugh T. Taggart's.", "India ink.", "Brittle, missing small sections, halved, and mounted on cloth backing.", "Includes 3 insets and index to points of interest.", "Available also through the Library of Congress Web site as a raster image.", "Phillips. Washington 512", "Vault", "DCP"], "number_former_id": ["https://www.loc.gov/item/88693289", "https://www.loc.gov/item/5502233"], "repository": ["Library of Congress Geography and Map Division Washington, D.C. 20540-4650 USA dcu"], "source_collection": ["Taggart, Hugh T. (Hugh Thomas), Taggart Estate map collection"], "subjects": ["Georgetown (Washington, D.C.)--Maps, Manuscript", "Real property--Washington (D.C.)--Maps", "United States--District of Columbia--Washington--Georgetown", "United States--District of Columbia--Washington"], "title": "A map of George Town with the additions : 1814"}, "language": ["english"], "location": ["united states", "washington d.c.", "district of columbia", "washington", "georgetown"], "location_city": ["washington"], "location_country": ["united states"], "location_state": ["district of columbia"], "mime_type": ["image/gif", "image/tiff", "image/jpeg", "image/jp2"], "number": ["http://www.loc.gov/item/5502233", "http://www.loc.gov/item/88693289", "88693289", "2021-08-26t14:37:37"], "number_former_id": ["http://www.loc.gov/item/88693289", "http://www.loc.gov/item/5502233"], "number_lccn": ["88693289"], "number_source_modified": ["2021-08-26t14:37:37"], "online_format": ["image"], "original_format": ["map"], "other_title": [], "partof": ["county landownership maps", "cultural landscapes", "cities and towns", "catalog", "american memory", "geography and map division"], "resources": [{"files": 1, "image": "https://tile.loc.gov/storage-services/service/gmd/gmd385/g3852/g3852g/la002257.gif", "url": "https://www.loc.gov/resource/g3852g.la002257/"}], "shelf_id": "G3852.G43G46 1814 .F4", "site": ["ammem", "catalog"], "subject": ["maps, manuscript", "washington (d.c.)", "washington", "united states", "maps", "district of columbia", "real property", "georgetown (washington, d.c.)", "georgetown"], "timestamp": "2021-08-28T23:29:05.645Z", "title": "A map of George Town with the additions : 1814", "url": "https://www.loc.gov/item/88693289/"}, {"access_restricted": false, "aka": ["http://hdl.loc.gov/loc.gmd/g3852g.la002238r", "http://www.loc.gov/item/88693301/", "http://www.loc.gov/resource/g3852g.la002238r/", "http://hdl.loc.gov/loc.gmd/g3852g.la002238v", "http://www.loc.gov/resource/g3852g.la002238v/", "http://lccn.loc.gov/88693301"], "campaigns": [], "contributor": ["taggart, hugh t. (hugh thomas)"], "date": "1843", "dates": ["1843-01-01T00:00:00Z"], "description": ["Cadastral survey maps showing landowners' names. \"Book 1839, 40, last part, Octo'r 28th 1843.\" Title from verso. Pen-and-ink. Soiled, fold-lined, and missing edge sections. Two incomplete surveys maps in ink and lead pencil on verso. Available also through the Library of Congress Web site as a raster image. Phillips. Washington 496 Vault DCP"], "digitized": true, "extract_timestamp": "2021-08-28T23:27:34.305Z", "group": ["gmd.mar", "catalog", "general-maps", "main-catalog"], "hassegments": false, "id": "http://www.loc.gov/item/88693301/", "image_url": ["https://tile.loc.gov/storage-services/service/gmd/gmd385/g3852/g3852g/la002238r.gif", "https://tile.loc.gov/storage-services/service/gmd/gmd385/g3852/g3852g/la002238r.gif#h=150&w=120", "https://tile.loc.gov/image-services/iiif/service:gmd:gmd385:g3852:g3852g:la002238r/full/pct:12.5/0/default.jpg#h=815&w=653", "https://tile.loc.gov/image-services/iiif/service:gmd:gmd385:g3852:g3852g:la002238r/full/pct:25/0/default.jpg#h=1631&w=1306"], "index": 9, "item": {"call_number": ["G3852.G43G46 1843 .N6"], "contributors": ["Taggart, Hugh T. (Hugh Thomas), 1844-1914."], "created_published": ["1843."], "date": "1843", "digital_id": ["http://hdl.loc.gov/loc.gmd/g3852g.la002238r", "http://hdl.loc.gov/loc.gmd/g3852g.la002238v"], "format": ["cartographic"], "language": ["eng"], "location": ["Washington (D.C.)", "Georgetown (Washington, D.C.)"], "medium": ["2 maps on 1 sheet : ms. ; 29 x 20 cm. and 27 x 24 cm., sheet 57 x 46 cm."], "notes": ["Cadastral survey maps showing landowners' names.", "\"Book 1839, 40, last part, Octo'r 28th 1843.\"", "Title from verso.", "Pen-and-ink.", "Soiled, fold-lined, and missing edge sections.", "Two incomplete surveys maps in ink and lead pencil on verso.", "Available also through the Library of Congress Web site as a raster image.", "Phillips. Washington 496", "Vault", "DCP"], "number_former_id": ["https://www.loc.gov/item/88693301", "https://www.loc.gov/item/5502245"], "repository": ["Library of Congress Geography and Map Division Washington, D.C. 20540-4650 USA dcu"], "source_collection": ["Taggart, Hugh T. (Hugh Thomas), Taggart Estate map collection"], "subjects": ["Georgetown (Washington, D.C.)--Maps, Manuscript", "Georgetown (Washington, D.C.)--Surveys--Maps", "Davidson, John,--active 19th century--Homes and haunts--Washington (D.C.)--Maps", "Real property--Washington (D.C.)--Maps", "Manuscript maps", "United States--District of Columbia--Washington--Georgetown", "United States--District of Columbia--Washington"], "title": "No. 1. Survey for John Davidson ; No. 2. Lots surveyed on 1st Street between Fred. & Fayette streets : [Georgetown, Washington D.C.]."}, "language": ["english"], "location": ["united states", "washington d.c.", "district of columbia", "washington", "georgetown"], "location_city": ["washington"], "location_country": ["united states"], "location_state": ["district of columbia"], "mime_type": ["image/gif", "image/tiff", "image/jpeg", "image/jp2"], "number": ["http://www.loc.gov/item/88693301", "88693301", "2021-08-26t15:27:55", "http://www.loc.gov/item/5502245"], "number_former_id": ["http://www.loc.gov/item/88693301", "http://www.loc.gov/item/5502245"], "number_lccn": ["88693301"], "number_source_modified": ["2021-08-26t15:27:55"], "online_format": ["image"], "original_format": ["map"], "other_title": [], "partof": ["county landownership maps", "cultural landscapes", "cities and towns", "catalog", "american memory", "geography and map division"], "resources": [{"caption": "Recto", "files": 1, "image": "https://tile.loc.gov/storage-services/service/gmd/gmd385/g3852/g3852g/la002238r.gif", "url": "https://www.loc.gov/resource/g3852g.la002238r/"}, {"caption": "Verso", "files": 1, "image": "https://tile.loc.gov/storage-services/service/gmd/gmd385/g3852/g3852g/la002238v.gif", "url": "https://www.loc.gov/resource/g3852g.la002238v/"}], "shelf_id": "G3852.G43G46 1843 .N6", "site": ["ammem", "catalog"], "subject": ["maps, manuscript", "surveys", "washington (d.c.)", "washington", "homes and haunts", "united states", "maps", "active 19th century", "davidson, john", "georgetown", "real property", "georgetown (washington, d.c.)", "manuscript maps", "district of columbia"], "timestamp": "2021-08-28T23:29:05.645Z", "title": "No. 1. Survey for John Davidson ; No. 2. Lots surveyed on 1st Street between Fred. & Fayette streets : [Georgetown, Washington D.C.].", "url": "https://www.loc.gov/item/88693301/"}, {"access_restricted": false, "aka": ["http://hdl.loc.gov/loc.gmd/g3852g.ct004294", "http://www.loc.gov/item/88693293/", "http://www.loc.gov/resource/g3852g.ct004294/", "http://lccn.loc.gov/88693293"], "campaigns": [], "contributor": ["carbery, lewis", "taggart, hugh t. (hugh thomas)", "carpenter, b. d. (benjamin d.)", "district of columbia. office of the surveyor"], "date": "1853", "dates": ["1853-01-01T00:00:00Z"], "description": ["Title devised by cataloger. On cloth backing in lead pencil: Profiles showing grading of Market St. east side and west side of Duck Lane etc., 1853. At lower left in lead pencil: Lewis Carbery, reported to Carpenter, Sept'r 1853. Pen-and-ink. Mounted on cloth backing. Available also through the Library of Congress Web site as a raster image. Phillips. Washington 517 Vault DCP"], "digitized": true, "extract_timestamp": "2021-08-28T23:27:34.305Z", "group": ["gmd.mar", "catalog", "general-maps", "main-catalog"], "hassegments": false, "id": "http://www.loc.gov/item/88693293/", "image_url": ["https://tile.loc.gov/storage-services/service/gmd/gmd385/g3852/g3852g/ct004294.gif", "https://tile.loc.gov/storage-services/service/gmd/gmd385/g3852/g3852g/ct004294.gif#h=116&w=150", "https://tile.loc.gov/image-services/iiif/service:gmd:gmd385:g3852:g3852g:ct004294/full/pct:12.5/0/default.jpg#h=650&w=841", "https://tile.loc.gov/image-services/iiif/service:gmd:gmd385:g3852:g3852g:ct004294/full/pct:25/0/default.jpg#h=1301&w=1682"], "index": 10, "item": {"call_number": ["G3852.G43N23 1853 .C3"], "contents": ["Market Street east side -- Market Street west side -- Duck Lane -- Frederick Street -- Green Street -- Washington Street -- Jefferson Street -- Congress Street."], "contributors": ["Carbery, Lewis.", "Carpenter, B. D. (Benjamin D.)", "Taggart, Hugh T. (Hugh Thomas), 1844-1914.", "District of Columbia. Office of the Surveyor."], "created_published": ["1853."], "date": "1853", "digital_id": ["http://hdl.loc.gov/loc.gmd/g3852g.ct004294"], "format": ["cartographic"], "language": ["eng"], "location": ["Washington (D.C.)", "Georgetown (Washington, D.C.)"], "medium": ["8 profiles on 1 sheet : ms. ; 6 x 33 cm. or smaller, sheet 45 x 58 cm."], "notes": ["Title devised by cataloger.", "On cloth backing in lead pencil: Profiles showing grading of Market St. east side and west side of Duck Lane etc., 1853.", "At lower left in lead pencil: Lewis Carbery, reported to Carpenter, Sept'r 1853.", "Pen-and-ink.", "Mounted on cloth backing.", "Available also through the Library of Congress Web site as a raster image.", "Phillips. Washington 517", "Vault", "DCP"], "number_former_id": ["https://www.loc.gov/item/88693293", "https://www.loc.gov/item/5502237"], "repository": ["Library of Congress Geography and Map Division Washington, D.C. 20540-4650 USA dcu"], "source_collection": ["Taggart, Hugh T. (Hugh Thomas), Taggart Estate map collection"], "subjects": ["Georgetown (Washington, D.C.)--Maps, Manuscript", "Streets--Washington (D.C.)--Planning--Maps", "Streets--Washington (D.C.)--Charts, diagrams, etc", "Manuscript maps", "United States--District of Columbia--Georgetown (Washington)", "United States--District of Columbia--Washington"], "title": "[Eight grade profiles of streets in Georgetown, Washington D.C.]."}, "language": ["english"], "location": ["washington d.c.", "georgetown", "washington", "united states", "district of columbia", "georgetown (washington)"], "location_city": ["georgetown (washington)", "washington"], "location_country": ["united states"], "location_state": ["district of columbia"], "mime_type": ["image/gif", "image/tiff", "image/jpeg", "image/jp2"], "number": ["2021-08-26t14:12:32", "88693293", "http://www.loc.gov/item/88693293", "http://www.loc.gov/item/5502237"], "number_former_id": ["http://www.loc.gov/item/88693293", "http://www.loc.gov/item/5502237"], "number_lccn": ["88693293"], "number_source_modified": ["2021-08-26t14:12:32"], "online_format": ["image"], "original_format": ["map"], "other_title": [], "partof": ["american memory", "cities and towns", "catalog", "geography and map division"], "resources": [{"files": 1, "image": "https://tile.loc.gov/storage-services/service/gmd/gmd385/g3852/g3852g/ct004294.gif", "url": "https://www.loc.gov/resource/g3852g.ct004294/"}], "shelf_id": "G3852.G43N23 1853 .C3", "site": ["ammem", "catalog"], "subject": ["maps, manuscript", "washington (d.c.)", "washington", "streets", "charts, diagrams, etc", "united states", "maps", "planning", "georgetown (washington)", "georgetown (washington, d.c.)", "manuscript maps", "district of columbia"], "timestamp": "2021-08-28T23:29:05.645Z", "title": "[Eight grade profiles of streets in Georgetown, Washington D.C.].", "url": "https://www.loc.gov/item/88693293/"}, {"access_restricted": false, "aka": ["http://www.loc.gov/item/88690900/", "http://www.loc.gov/resource/g3852l.la002378/", "https://hdl.loc.gov/loc.gmd/g3852l.la002378", "http://lccn.loc.gov/88690900"], "campaigns": [], "contributor": ["taggart, hugh t. (hugh thomas)", "bouscaren, w. s."], "date": "1797", "dates": ["1797-01-01T00:00:00Z"], "description": ["Cadastral survey map. India ink and watercolor. Soiled, fold-lined, and turn along fold lines. Includes notes and table of survey data. Available also through the Library of Congress Web site as a raster image. Vault DCP"], "digitized": true, "extract_timestamp": "2021-08-28T23:27:34.305Z", "group": ["gmd.mar", "catalog", "general-maps", "main-catalog"], "hassegments": false, "id": "http://www.loc.gov/item/88690900/", "image_url": ["https://tile.loc.gov/storage-services/service/gmd/gmd385/g3852/g3852l/la002378.gif", "https://tile.loc.gov/storage-services/service/gmd/gmd385/g3852/g3852l/la002378.gif#h=150&w=108", "https://tile.loc.gov/image-services/iiif/service:gmd:gmd385:g3852:g3852l:la002378/full/pct:12.5/0/default.jpg#h=2805&w=2023", "https://tile.loc.gov/image-services/iiif/service:gmd:gmd385:g3852:g3852l:la002378/full/pct:25/0/default.jpg#h=5610&w=4046"], "index": 11, "item": {"call_number": ["G3852.L6G46 1797 .B6"], "contributors": ["Bouscaren, W. S.", "Taggart, Hugh T. (Hugh Thomas), 1844-1914."], "created_published": ["1905."], "date": "1797", "digital_id": ["https://hdl.loc.gov/loc.gmd/g3852l.la002378"], "format": ["cartographic"], "language": ["eng"], "location": ["Washington (D.C.)", "Long Meadows (Washington, D.C.)"], "medium": ["1 map on 2 sheets : ms., col., tracing linen ; 173 x 122 cm., sheets 95 x 135 cm. and 94 x 135 cm."], "notes": ["Cadastral survey map.", "India ink and watercolor.", "Soiled, fold-lined, and turn along fold lines.", "Includes notes and table of survey data.", "Available also through the Library of Congress Web site as a raster image.", "Vault", "DCP"], "number_former_id": ["https://www.loc.gov/item/88690900", "https://www.loc.gov/item/5500151"], "repository": ["Library of Congress Geography and Map Division Washington, D.C. 20540-4650 USA dcu"], "source_collection": ["Taggart, Hugh T. (Hugh Thomas), Taggart Estate map collection"], "subjects": ["Long Meadows (Washington, D.C.)--Maps, Manuscript--Early works to 1800", "Long Meadows (Washington, D.C.)--Surveys--Maps--Early works to 1800", "Real property--Washington (D.C.)--Maps--Early works to 1800", "Stoddert, Benjamin,--1751-1813--Estate--Maps--Early works to 1800", "Stoddert, Rebecca--Estate--Maps--Early works to 1800", "Campbell, William,--active 18th century--Estate--Maps--Early works to 1800", "Manuscript maps--Early works to 1800", "United States--District of Columbia--Washington--Long Meadows"], "title": "Map of Long Meadows, embracing the re-survey of the Wilderness, Queen's Hazard, and parts of Inclosure, Grange, and Mure and Chance : as per deed recorded in liber B, folio 684, from Benjamin Stoddert and wife Rebecca to William Campbell : deed dated March 26th 1797, recorded April 20th 1797 : [N.E. Washington D.C.]"}, "language": ["english"], "location": ["united states", "washington d.c.", "district of columbia", "washington", "long meadows"], "location_city": ["washington"], "location_country": ["united states"], "location_state": ["district of columbia"], "mime_type": ["image/gif", "image/tiff", "image/jpeg", "image/jp2"], "number": ["http://www.loc.gov/item/88690900", "http://www.loc.gov/item/5500151", "88690900", "2021-08-26t14:06:34"], "number_former_id": ["http://www.loc.gov/item/88690900", "http://www.loc.gov/item/5500151"], "number_lccn": ["88690900"], "number_source_modified": ["2021-08-26t14:06:34"], "online_format": ["image"], "original_format": ["map"], "other_title": [], "partof": ["county landownership maps", "cultural landscapes", "cities and towns", "catalog", "american memory", "geography and map division"], "resources": [{"files": 1, "image": "https://tile.loc.gov/storage-services/service/gmd/gmd385/g3852/g3852l/la002378.gif", "url": "https://www.loc.gov/resource/g3852l.la002378/"}], "shelf_id": "G3852.L6G46 1797 .B6", "site": ["ammem", "catalog"], "subject": ["maps, manuscript", "surveys", "long meadows (washington, d.c.)", "estate", "washington (d.c.)", "washington", "campbell, william", "united states", "maps", "early works to 1800", "district of columbia", "long meadows", "active 18th century", "real property", "stoddert, benjamin", "manuscript maps", "stoddert, rebecca"], "timestamp": "2021-08-28T23:29:05.645Z", "title": "Map of Long Meadows, embracing the re-survey of the Wilderness, Queen's Hazard, and parts of Inclosure, Grange, and Mure and Chance : as per deed recorded in liber B, folio 684, from Benjamin Stoddert and wife Rebecca to William Campbell : deed dated March 26th 1797, recorded April 20th 1797 : [N.E. Washington D.C.]", "url": "https://www.loc.gov/item/88690900/"}, {"access_restricted": false, "aka": ["http://www.loc.gov/item/88690947/", "http://hdl.loc.gov/loc.gmd/g3852m.ct005030", "http://www.loc.gov/resource/g3852m.ct005030/", "http://lccn.loc.gov/88690947"], "campaigns": [], "contributor": ["district of columbia. office of the surveyor", "taggart, hugh t. (hugh thomas)"], "date": "1910", "dates": ["1910-01-01T00:00:00Z"], "description": ["Shows existing and planned sections of Massachusetts Avenue and lands to be taken for its extension. Title devised by cataloger. From the Taggart Estate papers. Blueprint. In corners: 640 (in reverse image). LC copy fold-lined and annotated in pencil. Available also through the Library of Congress Web site as a raster image. DCP"], "digitized": true, "extract_timestamp": "2021-08-28T23:27:34.305Z", "group": ["gmd.mar", "catalog", "general-maps", "main-catalog"], "hassegments": false, "id": "http://www.loc.gov/item/88690947/", "image_url": ["https://tile.loc.gov/storage-services/service/gmd/gmd385/g3852/g3852m/ct005030.gif", "https://tile.loc.gov/storage-services/service/gmd/gmd385/g3852/g3852m/ct005030.gif#h=97&w=150", "https://tile.loc.gov/image-services/iiif/service:gmd:gmd385:g3852:g3852m:ct005030/full/pct:12.5/0/default.jpg#h=978&w=1520", "https://tile.loc.gov/image-services/iiif/service:gmd:gmd385:g3852:g3852m:ct005030/full/pct:25/0/default.jpg#h=1957&w=3040"], "index": 12, "item": {"call_number": ["G3852.M36G45 191- .D5"], "contributors": ["District of Columbia. Office of the Surveyor.", "Taggart, Hugh T. (Hugh Thomas), 1844-1914."], "created_published": ["[Washington] : The Office, [191-]"], "date": "1910", "digital_id": ["http://hdl.loc.gov/loc.gmd/g3852m.ct005030"], "format": ["cartographic"], "language": ["eng"], "location": ["Washington (D.C.)", "Massachusetts Avenue (Washington, D.C.)", "American University Park (Washington, D.C.)", "Spring Valley (Washington, D.C.)"], "medium": ["1 map : photocopy ; 66 x 104 cm."], "notes": ["Shows existing and planned sections of Massachusetts Avenue and lands to be taken for its extension.", "Title devised by cataloger.", "From the Taggart Estate papers.", "Blueprint.", "In corners: 640 (in reverse image).", "LC copy fold-lined and annotated in pencil.", "Available also through the Library of Congress Web site as a raster image.", "DCP"], "number_former_id": ["https://www.loc.gov/item/88690947", "https://www.loc.gov/item/5500198"], "repository": ["Library of Congress Geography and Map Division Washington, D.C. 20540-4650 USA dcu"], "source_collection": ["Taggart, Hugh T. (Hugh Thomas), Taggart Estate map collection"], "subjects": ["Massachusetts Avenue (Washington, D.C.)--Maps", "American University Park (Washington, D.C.)--Maps", "Spring Valley (Washington, D.C.)--Maps", "Streets--Washington (D.C.)--Planning--Maps", "Real property--Washington (D.C.)--Maps", "United States--District of Columbia--Washington--Massachusetts Avenue", "United States--District of Columbia--Washington--American University Park", "United States--District of Columbia--Washington--Spring Valley", "United States--District of Columbia--Washington"], "title": "[Cadastral map of Massachusetts Avenue N.W. and adjacent parts of American University Park and Spring Valley, Washington D.C.]"}, "language": ["english"], "location": ["washington d.c.", "massachusetts avenue", "washington", "united states", "american university park", "district of columbia", "spring valley"], "location_city": ["washington"], "location_country": ["united states"], "location_state": ["district of columbia"], "mime_type": ["image/gif", "image/tiff", "image/jpeg", "image/jp2"], "number": ["2021-08-26t14:34:19", "88690947", "http://www.loc.gov/item/88690947", "http://www.loc.gov/item/5500198"], "number_former_id": ["http://www.loc.gov/item/88690947", "http://www.loc.gov/item/5500198"], "number_lccn": ["88690947"], "number_source_modified": ["2021-08-26t14:34:19"], "online_format": ["image"], "original_format": ["map"], "other_title": [], "partof": ["american memory", "cities and towns", "catalog", "geography and map division"], "resources": [{"files": 1, "image": "https://tile.loc.gov/storage-services/service/gmd/gmd385/g3852/g3852m/ct005030.gif", "url": "https://www.loc.gov/resource/g3852m.ct005030/"}], "shelf_id": "G3852.M36G45 191- .D5", "site": ["ammem", "catalog"], "subject": ["washington (d.c.)", "spring valley (washington, d.c.)", "massachusetts avenue", "massachusetts avenue (washington, d.c.)", "streets", "washington", "spring valley", "united states", "maps", "american university park", "planning", "real property", "american university park (washington, d.c.)", "district of columbia"], "timestamp": "2021-08-28T23:29:05.645Z", "title": "[Cadastral map of Massachusetts Avenue N.W. and adjacent parts of American University Park and Spring Valley, Washington D.C.]", "url": "https://www.loc.gov/item/88690947/"}, {"access_restricted": false, "aka": ["http://www.loc.gov/item/88693303/", "http://www.loc.gov/resource/g3852r.ct004335/", "http://hdl.loc.gov/loc.gmd/g3852r.ct004335", "http://lccn.loc.gov/88693303"], "campaigns": [], "contributor": ["taggart, hugh t. (hugh thomas)"], "date": "1858", "dates": ["1858-01-01T00:00:00Z"], "description": ["Covers R Street between 34th and 35th streets N.W. On verso in ink: Profile of 8th Street between Fayette & Frederick streets--1858 by order of Corporation, Geo'town D.C. Pen-and-ink and orange wash. Soiled and torn. Includes notes and 3 cross-sections. Available also through the Library of Congress Web site as a raster image. Phillips. Washington 497 Vault DCP"], "digitized": true, "extract_timestamp": "2021-08-28T23:27:42.534Z", "group": ["gmd.mar", "catalog", "general-maps", "main-catalog"], "hassegments": false, "id": "http://www.loc.gov/item/88693303/", "image_url": ["https://tile.loc.gov/storage-services/service/gmd/gmd385/g3852/g3852r/ct004335.gif", "https://tile.loc.gov/storage-services/service/gmd/gmd385/g3852/g3852r/ct004335.gif#h=98&w=150", "https://tile.loc.gov/image-services/iiif/service:gmd:gmd385:g3852:g3852r:ct004335/full/pct:12.5/0/default.jpg#h=520&w=795", "https://tile.loc.gov/image-services/iiif/service:gmd:gmd385:g3852:g3852r:ct004335/full/pct:25/0/default.jpg#h=1041&w=1590"], "index": 13, "item": {"call_number": ["G3852.R14B5 1858 .P7"], "contributors": ["Taggart, Hugh T. (Hugh Thomas), 1844-1914."], "created_published": ["1858."], "date": "1858", "digital_id": ["http://hdl.loc.gov/loc.gmd/g3852r.ct004335"], "format": ["cartographic"], "language": ["eng"], "location": ["Washington (D.C.)", "R Street (Washington, D.C.)", "Georgetown (Washington, D.C.)"], "medium": ["1 profile : ms., col. ; 15 x 21 cm., on sheet 37 x 55 cm."], "notes": ["Covers R Street between 34th and 35th streets N.W.", "On verso in ink: Profile of 8th Street between Fayette & Frederick streets--1858 by order of Corporation, Geo'town D.C.", "Pen-and-ink and orange wash.", "Soiled and torn.", "Includes notes and 3 cross-sections.", "Available also through the Library of Congress Web site as a raster image.", "Phillips. Washington 497", "Vault", "DCP"], "number_former_id": ["https://www.loc.gov/item/88693303", "https://www.loc.gov/item/5502247"], "repository": ["Library of Congress Geography and Map Division Washington, D.C. 20540-4650 USA dcu"], "subjects": ["R Street (Washington, D.C.)--Surveys--Maps", "R Street (Washington, D.C.)--Maps, Manuscript", "Streets--Washington (D.C.)--Charts, diagrams, etc", "Georgetown (Washington, D.C.)--Maps, Manuscript", "Manuscript maps", "United States--District of Columbia--Washington--R Street", "United States--District of Columbia--Washington--Georgetown"], "title": "Profile of 8th Street between Fayette and Frederick, laid off for graduation : by order of the Corporation in August 1858 : [Georgetown, Washington D.C.]"}, "language": ["english"], "location": ["washington d.c.", "georgetown", "r street", "washington", "united states", "district of columbia"], "location_city": ["washington"], "location_country": ["united states"], "location_state": ["district of columbia"], "mime_type": ["image/gif", "image/tiff", "image/jpeg", "image/jp2"], "number": ["2021-08-26t13:54:10", "http://www.loc.gov/item/88693303", "http://www.loc.gov/item/5502247", "88693303"], "number_former_id": ["http://www.loc.gov/item/88693303", "http://www.loc.gov/item/5502247"], "number_lccn": ["88693303"], "number_source_modified": ["2021-08-26t13:54:10"], "online_format": ["image"], "original_format": ["map"], "other_title": [], "partof": ["american memory", "cities and towns", "catalog", "geography and map division"], "resources": [{"files": 1, "image": "https://tile.loc.gov/storage-services/service/gmd/gmd385/g3852/g3852r/ct004335.gif", "url": "https://www.loc.gov/resource/g3852r.ct004335/"}], "shelf_id": "G3852.R14B5 1858 .P7", "site": ["ammem", "catalog"], "subject": ["washington (d.c.)", "surveys", "r street", "maps, manuscript", "washington", "streets", "charts, diagrams, etc", "georgetown", "united states", "maps", "district of columbia", "r street (washington, d.c.)", "georgetown (washington, d.c.)", "manuscript maps"], "timestamp": "2021-08-28T23:29:05.645Z", "title": "Profile of 8th Street between Fayette and Frederick, laid off for graduation : by order of the Corporation in August 1858 : [Georgetown, Washington D.C.]", "url": "https://www.loc.gov/item/88693303/"}, {"access_restricted": false, "aka": ["http://www.loc.gov/resource/g3852t.ct006225r/", "http://www.loc.gov/item/88693343/", "http://hdl.loc.gov/loc.gmd/g3852t.ct006225r", "http://hdl.loc.gov/loc.gmd/g3852t.ct006225v", "http://www.loc.gov/resource/g3852t.ct006225v/", "http://lccn.loc.gov/88693343"], "campaigns": [], "contributor": ["carbery, lewis", "taggart, hugh t. (hugh thomas)"], "date": "1856", "dates": ["1856-01-01T00:00:00Z"], "description": ["Washington Street profile covers 30th Street between Q and R streets N.W. Fayette Street profile covers 35th Street between Volta Place and Wisconsin Avenue N.W. Alternate title: Profile of Washington & Fayette streets. Oriented with north to the left. Black, brown, blue inks, and lead pencil. Soiled and cracked at edges. Includes notes, statistical tables, computations, and outline maps of both streets. Available also through the Library of Congress Web site as a raster image. Phillips. Washington 498 Vault DCP"], "digitized": true, "extract_timestamp": "2021-08-28T23:27:34.305Z", "group": ["gmd.mar", "catalog", "general-maps", "main-catalog"], "hassegments": false, "id": "http://www.loc.gov/item/88693343/", "image_url": ["https://tile.loc.gov/storage-services/service/gmd/gmd385/g3852/g3852t/ct006225r.gif", "https://tile.loc.gov/storage-services/service/gmd/gmd385/g3852/g3852t/ct006225r.gif#h=119&w=150", "https://tile.loc.gov/image-services/iiif/service:gmd:gmd385:g3852:g3852t:ct006225r/full/pct:12.5/0/default.jpg#h=674&w=850", "https://tile.loc.gov/image-services/iiif/service:gmd:gmd385:g3852:g3852t:ct006225r/full/pct:25/0/default.jpg#h=1349&w=1701"], "index": 14, "item": {"call_number": ["G3852.T4615N23 1856 .C3"], "contents": ["Graduation of Washington Street from the north line of Stoddart Street to south line of Road Street : as established by law -- Profile of Fayette Street from south side of 4th to centre of High Street : Oct'r 3rd, 16th & 20th 1856, [Oct'r] 22nd, 23rd, 24th."], "contributors": ["Carbery, Lewis.", "Taggart, Hugh T. (Hugh Thomas), 1844-1914."], "created_published": ["1856."], "date": "1856", "digital_id": ["http://hdl.loc.gov/loc.gmd/g3852t.ct006225r", "http://hdl.loc.gov/loc.gmd/g3852t.ct006225v"], "format": ["cartographic"], "language": ["eng"], "location": ["Washington (D.C.)", "Thirtieth Street (Washington, D.C.)", "Thirty-Fifth Street (Washington, D.C.)"], "medium": ["2 profiles on 1 sheet : both sides, ms., col. ; 28 x 46 cm. and 21 x 55 cm., sheet 45 x 57 cm."], "notes": ["Washington Street profile covers 30th Street between Q and R streets N.W. Fayette Street profile covers 35th Street between Volta Place and Wisconsin Avenue N.W.", "Alternate title: Profile of Washington & Fayette streets.", "Oriented with north to the left.", "Black, brown, blue inks, and lead pencil.", "Soiled and cracked at edges.", "Includes notes, statistical tables, computations, and outline maps of both streets.", "Available also through the Library of Congress Web site as a raster image.", "Phillips. Washington 498", "Vault", "DCP"], "number_former_id": ["https://www.loc.gov/item/88693343", "https://www.loc.gov/item/5502287"], "repository": ["Library of Congress Geography and Map Division Washington, D.C. 20540-4650 USA dcu"], "source_collection": ["Taggart, Hugh T. (Hugh Thomas), Taggart Estate map collection"], "subjects": ["Thirtieth Street (Washington, D.C.)--Maps, Manuscript", "Thirty-Fifth Street (Washington, D.C.)--Maps, Manuscript", "Streets--Washington (D.C.)--Charts, diagrams, etc", "Manuscript maps", "United States--District of Columbia--Washington"], "title": "Profile of Washington & Fayette streets, Georgetown, D.C."}, "language": ["english"], "location": ["washington d.c.", "fifth street", "thirty", "washington", "united states", "district of columbia", "thirtieth street"], "location_city": ["washington"], "location_country": ["united states"], "location_state": ["district of columbia"], "mime_type": ["image/gif", "image/tiff", "image/jpeg", "image/jp2"], "number": ["http://www.loc.gov/item/5502287", "88693343", "2021-08-26t14:21:58", "http://www.loc.gov/item/88693343"], "number_former_id": ["http://www.loc.gov/item/88693343", "http://www.loc.gov/item/5502287"], "number_lccn": ["88693343"], "number_source_modified": ["2021-08-26t14:21:58"], "online_format": ["image"], "original_format": ["map"], "other_title": [], "partof": ["american memory", "general maps", "catalog", "geography and map division", "cities and towns"], "resources": [{"caption": "Recto", "files": 1, "image": "https://tile.loc.gov/storage-services/service/gmd/gmd385/g3852/g3852t/ct006225r.gif", "url": "https://www.loc.gov/resource/g3852t.ct006225r/"}, {"caption": "Verso", "files": 1, "image": "https://tile.loc.gov/storage-services/service/gmd/gmd385/g3852/g3852t/ct006225v.gif", "url": "https://www.loc.gov/resource/g3852t.ct006225v/"}], "shelf_id": "G3852.T4615N23 1856 .C3", "site": ["ammem", "catalog"], "subject": ["washington (d.c.)", "thirty-fifth street (washington, d.c.)", "washington", "streets", "charts, diagrams, etc", "maps, manuscript", "united states", "thirtieth street (washington, d.c.)", "district of columbia", "manuscript maps"], "timestamp": "2021-08-28T23:29:05.645Z", "title": "Profile of Washington & Fayette streets, Georgetown, D.C.", "url": "https://www.loc.gov/item/88693343/"}, {"access_restricted": false, "aka": ["http://hdl.loc.gov/loc.gmd/g3852t.ct006216r", "http://www.loc.gov/resource/g3852t.ct006216r/", "http://hdl.loc.gov/loc.gmd/g3852t.ct006216v", "http://www.loc.gov/item/88693335/", "http://www.loc.gov/resource/g3852t.ct006216v/", "http://lccn.loc.gov/88693335"], "campaigns": [], "contributor": ["carbery, lewis", "taggart, hugh t. (hugh thomas)"], "date": "1858", "dates": ["1858-01-01T00:00:00Z"], "description": ["Covers Thirty-Fifth Street and Wisconsin Avenue N.W., Georgetown, Washington D.C. Pen-and-ink, lead pencil, and blue wash. Ink-stained, faced with gauze, and mounted on cloth backing. Includes notes. Available also through the Library of Congress Web site as a raster image. Phillips. Washington 499 Vault DCP"], "digitized": true, "extract_timestamp": "2021-08-28T23:27:34.305Z", "group": ["gmd.mar", "catalog", "general-maps", "main-catalog"], "hassegments": false, "id": "http://www.loc.gov/item/88693335/", "image_url": ["https://tile.loc.gov/storage-services/service/gmd/gmd385/g3852/g3852t/ct006216r.gif", "https://tile.loc.gov/storage-services/service/gmd/gmd385/g3852/g3852t/ct006216r.gif#h=37&w=150", "https://tile.loc.gov/image-services/iiif/service:gmd:gmd385:g3852:g3852t:ct006216r/full/pct:12.5/0/default.jpg#h=218&w=897", "https://tile.loc.gov/image-services/iiif/service:gmd:gmd385:g3852:g3852t:ct006216r/full/pct:25/0/default.jpg#h=437&w=1794"], "index": 15, "item": {"call_number": ["G3852.T462N23 1858 .C3"], "contents": ["1st cross section beginning at 179 feet on east line of Fayette Street -- 2nd cross section 21 feet from the 1st -- 3rd cross section 47 feet from the 2nd -- 4th cross section 30 feet from the 3rd."], "contributors": ["Carbery, Lewis.", "Taggart, Hugh T. (Hugh Thomas), 1844-1914."], "created_published": ["1858."], "date": "1858", "digital_id": ["http://hdl.loc.gov/loc.gmd/g3852t.ct006216r", "http://hdl.loc.gov/loc.gmd/g3852t.ct006216v"], "format": ["cartographic"], "language": ["eng"], "location": ["Washington (D.C.)", "Thirty-Fifth Street (Washington, D.C.)", "Wisconsin Avenue (Washington, D.C.)"], "medium": ["4 profiles on 1 sheet : ms., col. ; 12 x 13 cm. or smaller, sheet 14 x 61 cm."], "notes": ["Covers Thirty-Fifth Street and Wisconsin Avenue N.W., Georgetown, Washington D.C.", "Pen-and-ink, lead pencil, and blue wash.", "Ink-stained, faced with gauze, and mounted on cloth backing.", "Includes notes.", "Available also through the Library of Congress Web site as a raster image.", "Phillips. Washington 499", "Vault", "DCP"], "number_former_id": ["https://www.loc.gov/item/88693335", "https://www.loc.gov/item/5502279"], "repository": ["Library of Congress Geography and Map Division Washington, D.C. 20540-4650 USA dcu"], "source_collection": ["Taggart, Hugh T. (Hugh Thomas), Taggart Estate map collection"], "subjects": ["Thirty-Fifth Street (Washington, D.C.)--Maps, Manuscript", "Wisconsin Avenue (Washington, D.C.)--Maps, Manuscript", "Streets--Washington (D.C.)--Planning--Maps", "Streets--Washington (D.C.)--Charts, diagrams, etc", "Manuscript maps", "United States--District of Columbia--Washington--Thirty-Fifth Street", "United States--District of Columbia--Washington--Wisconsin Avenue", "United States--District of Columbia--Washington"], "title": "Profiles of a piece of excavation lying between the intersection of the east line of Fayette Street and the west line of the extension of High Street : the material being wanted for the graduation of High Street extended"}, "language": ["english"], "location": ["washington d.c.", "fifth street", "thirty", "washington", "wisconsin avenue", "united states", "district of columbia"], "location_country": ["united states"], "location_county": ["washington"], "location_state": ["district of columbia"], "mime_type": ["image/gif", "image/tiff", "image/jpeg", "image/jp2"], "number": ["88693335", "http://www.loc.gov/item/88693335", "2021-08-26t14:28:58", "http://www.loc.gov/item/5502279"], "number_former_id": ["http://www.loc.gov/item/88693335", "http://www.loc.gov/item/5502279"], "number_lccn": ["88693335"], "number_source_modified": ["2021-08-26t14:28:58"], "online_format": ["image"], "original_format": ["map"], "other_title": [], "partof": ["american memory", "cities and towns", "catalog", "geography and map division"], "resources": [{"caption": "Recto", "files": 1, "image": "https://tile.loc.gov/storage-services/service/gmd/gmd385/g3852/g3852t/ct006216r.gif", "url": "https://www.loc.gov/resource/g3852t.ct006216r/"}, {"caption": "Verso", "files": 1, "image": "https://tile.loc.gov/storage-services/service/gmd/gmd385/g3852/g3852t/ct006216v.gif", "url": "https://www.loc.gov/resource/g3852t.ct006216v/"}], "shelf_id": "G3852.T462N23 1858 .C3", "site": ["ammem", "catalog"], "subject": ["wisconsin avenue (washington, d.c.)", "washington (d.c.)", "maps, manuscript", "washington", "maps", "streets", "charts, diagrams, etc", "wisconsin avenue", "united states", "thirty-fifth street (washington, d.c.)", "planning", "thirty-fifth street", "manuscript maps", "district of columbia"], "timestamp": "2021-08-28T23:29:05.645Z", "title": "Profiles of a piece of excavation lying between the intersection of the east line of Fayette Street and the west line of the extension of High Street : the material being wanted for the graduation of High Street extended", "url": "https://www.loc.gov/item/88693335/"}, {"access_restricted": false, "aka": ["http://www.loc.gov/item/2013591600/", "http://www.loc.gov/resource/g4380m.ghi02/", "http://www.loc.gov/resource/g4380m.ghi01/", "https://hdl.loc.gov/loc.gmd/g4380m.ghi02", "https://hdl.loc.gov/loc.gmd/g4380m.ghi03", "https://hdl.loc.gov/loc.gmd/g4380m.ghi01", "http://www.loc.gov/resource/g4380m.ghi03/", "http://lccn.loc.gov/2013591600"], "campaigns": [], "date": "1784", "dates": ["1784-01-01T00:00:00Z"], "description": ["This record covers single maps of Hawaii, which are not represented in the LC database by separate catalog records. This collection includes single printed maps, photocopies of single maps as well as multi-sheet single maps, and plates from atlases, books and periodicals. To request a specific map or for more information, contact a reference librarian in the Geography & Map Division (202) 707-6277 or through the \"Ask a librarian\" link through the Geography & Map Division website https://www.loc.gov/rr/geogmap/. Title supplied by cataloger. Maps and the folders in which they are stored are both displayed in the digital images. The information on the folders is incomplete and may not reflect current research. When the map may be within copyright, only the folder is displayed digitally. Available also through the Library of Congress Web site as a raster image. Most maps in English. Some maps in French. Drawers 1-3."], "digitized": true, "extract_timestamp": "2021-08-28T23:27:34.305Z", "group": ["gmd.mar", "catalog", "general-maps", "main-catalog"], "hassegments": true, "id": "http://www.loc.gov/item/2013591600/", "image_url": ["https://tile.loc.gov/storage-services/service/gmd/gmd438m/g4380m/g4380m/ghi01/hi0101.gif", "https://tile.loc.gov/storage-services/service/gmd/gmd438m/g4380m/g4380m/ghi01/hi0101.gif#h=93&w=150", "https://tile.loc.gov/image-services/iiif/service:gmd:gmd438m:g4380m:g4380m:ghi01:hi0101/full/pct:12.5/0/default.jpg#h=360&w=580", "https://tile.loc.gov/image-services/iiif/service:gmd:gmd438m:g4380m:g4380m:ghi01:hi0101/full/pct:25/0/default.jpg#h=720&w=1161"], "index": 16, "item": {"call_number": ["G4380 coll .M3"], "created_published": ["[Various places] : [various publishers], [1784-1965]"], "date": "1784", "digital_id": ["https://hdl.loc.gov/loc.gmd/g4380m.ghi01", "https://hdl.loc.gov/loc.gmd/g4380m.ghi02", "https://hdl.loc.gov/loc.gmd/g4380m.ghi03"], "format": ["cartographic", "collection"], "genre": ["Maps"], "language": ["eng", "fre"], "location": ["Hawaii"], "medium": ["3 drawers of maps : some color, some hand colored, some photocopies ; various sizes."], "notes": ["This record covers single maps of Hawaii, which are not represented in the LC database by separate catalog records. This collection includes single printed maps, photocopies of single maps as well as multi-sheet single maps, and plates from atlases, books and periodicals. To request a specific map or for more information, contact a reference librarian in the Geography & Map Division (202) 707-6277 or through the \"Ask a librarian\" link through the Geography & Map Division website https://www.loc.gov/rr/geogmap/.", "Title supplied by cataloger.", "Maps and the folders in which they are stored are both displayed in the digital images. The information on the folders is incomplete and may not reflect current research. When the map may be within copyright, only the folder is displayed digitally.", "Available also through the Library of Congress Web site as a raster image.", "Most maps in English. Some maps in French.", "Drawers 1-3."], "number_former_id": ["https://www.loc.gov/item/2013591600", "https://www.loc.gov/item/17960541"], "other_title": ["Hawaii title collection--general"], "repository": ["Library of Congress Geography and Map Division Washington, D.C. 20540-4650 USA dcu"], "subjects": ["Hawaii--Maps", "United States--Hawaii"], "title": "[Maps of Hawaii, from 1784 to 1965]."}, "language": ["french", "english"], "location": ["united states", "hawaii"], "location_country": ["united states"], "location_state": ["hawaii"], "mime_type": ["image/gif", "image/tiff", "image/jpeg", "image/jp2"], "number": ["http://www.loc.gov/item/2013591600", "2021-08-26t07:25:59", "http://www.loc.gov/item/17960541", "sheet", "2013591600"], "number_carrier_type": ["sheet"], "number_former_id": ["http://www.loc.gov/item/2013591600", "http://www.loc.gov/item/17960541"], "number_lccn": ["2013591600"], "number_source_modified": ["2021-08-26t07:25:59"], "online_format": ["image"], "original_format": ["map", "collection"], "other_title": ["Hawaii title collection--general"], "partof": ["american memory", "general maps", "catalog", "geography and map division"], "resources": [{"caption": "Drawer 1", "captions": "https://tile.loc.gov/storage-services/service/gmd/gmd438m/g4380m/g4380m/ghi01/captions.txt", "files": 37, "image": "https://tile.loc.gov/storage-services/service/gmd/gmd438m/g4380m/g4380m/ghi01/hi0101.gif", "search": "https://www.loc.gov/search/?all=true&c=200&fa=segmentof:g4380m.ghi01/&fo=json&sb=shelf-id&sq=group:gmd.mar+AND+number_source_modified:%5B2021-08-26+TO+2021-08-27%5D&st=gallery", "segments": 37, "url": "https://www.loc.gov/resource/g4380m.ghi01/"}, {"caption": "Drawer 2", "captions": "https://tile.loc.gov/storage-services/service/gmd/gmd438m/g4380m/g4380m/ghi02/captions.txt", "files": 34, "image": "https://tile.loc.gov/storage-services/service/gmd/gmd438m/g4380m/g4380m/ghi02/hi020101.gif", "search": "https://www.loc.gov/search/?all=true&c=200&fa=segmentof:g4380m.ghi02/&fo=json&sb=shelf-id&sq=group:gmd.mar+AND+number_source_modified:%5B2021-08-26+TO+2021-08-27%5D&st=gallery", "segments": 34, "url": "https://www.loc.gov/resource/g4380m.ghi02/"}, {"caption": "Drawer 3", "captions": "https://tile.loc.gov/storage-services/service/gmd/gmd438m/g4380m/g4380m/ghi03/captions.txt", "files": 8, "image": "https://tile.loc.gov/storage-services/service/gmd/gmd438m/g4380m/g4380m/ghi03/hi0301.gif", "search": "https://www.loc.gov/search/?all=true&c=200&fa=segmentof:g4380m.ghi03/&fo=json&sb=shelf-id&sq=group:gmd.mar+AND+number_source_modified:%5B2021-08-26+TO+2021-08-27%5D&st=gallery", "segments": 8, "url": "https://www.loc.gov/resource/g4380m.ghi03/"}], "segments": [{"count": 34, "link": "https://www.loc.gov/search/?all=true&c=200&fa=segmentof:g4380m.ghi02/&fo=json&sb=shelf-id&sq=group:gmd.mar+AND+number_source_modified:%5B2021-08-26+TO+2021-08-27%5D&st=gallery", "url": "https://www.loc.gov/resource/g4380m.ghi02/"}, {"count": 37, "link": "https://www.loc.gov/search/?all=true&c=200&fa=segmentof:g4380m.ghi01/&fo=json&sb=shelf-id&sq=group:gmd.mar+AND+number_source_modified:%5B2021-08-26+TO+2021-08-27%5D&st=gallery", "url": "https://www.loc.gov/resource/g4380m.ghi01/"}, {"count": 8, "link": "https://www.loc.gov/search/?all=true&c=200&fa=segmentof:g4380m.ghi03/&fo=json&sb=shelf-id&sq=group:gmd.mar+AND+number_source_modified:%5B2021-08-26+TO+2021-08-27%5D&st=gallery", "url": "https://www.loc.gov/resource/g4380m.ghi03/"}], "shelf_id": "G4380 coll .M3", "site": ["ammem", "catalog"], "subject": ["united states", "maps", "hawaii"], "timestamp": "2021-08-28T23:29:05.645Z", "title": "[Maps of Hawaii, from 1784 to 1965].", "url": "https://www.loc.gov/item/2013591600/"}]}